Workbook

Sheet 00_Cover
A1: InterGlobe Aviation Equity Research Model
A2: Historical analysis, driver-based forecast and discounted cash flow valuation
A4: Purpose
A5: Airline operating analysis, financial forecasting, unlevered cash flow, WACC and DCF valuation.
A7: Key Outputs
A8: FY2026A revenue | B8: INR crore | C8: ='07_Income_Statement'!E11 -> 84961.9
A9: FY2031E revenue | B9: INR crore | C9: ='07_Income_Statement'!J11 -> 153031.25
A10: FY2031E EBIT margin | B10: % | C10: ='07_Income_Statement'!J25 -> 0.062176512
A11: FY2031E unlevered free cash flow | B11: INR crore | C11: ='09_Cash_Flow'!J16 -> 3839.6436
A12: Base-case implied value per share | B12: INR per share | C12: ='11_DCF'!C33 -> 0
A13: Market price (07-Sep-2026) | B13: INR per share | C13: ='12_Reverse_DCF'!C7 -> 5001
A17: Model Flow
A18: Historical financials and operating KPIs
A19: Industry context and historical analysis
A20: Operating drivers and income statement
A21: Fleet, lease, working-capital and finance schedules
A22: Unlevered free cash flow
A23: Operating scenarios, DCF and reverse DCF
A26: Workbook Sections
A27: Sources and raw data | B27: Sheets 01 to 04
A28: Historical analysis | B28: Sheet 05
A29: Forecast model | B29: Sheets 06 to 08
A30: Cash flow and valuation | B30: Sheets 09 to 12
A32: Color Convention
A33: Blue font | B33: Editable assumptions and hardcoded inputs
A34: Green font | B34: Links to other worksheets
A35: Black font | B35: Formulas and calculations
A36: Scope | B36: Independent equity research model; not investment advice.

Sheet 01_Sources
A1: Sources and References
A2: Company reports used for the historical financial statements
A3: FY2016 is standalone under previous GAAP; FY2017 onward is consolidated under Ind AS.
A4: Annual Reports
A5: Period | B5: Source document | C5: Reporting basis | D5: File name
A6: FY2016 | B6: Annual Report FY2016 | C6: Standalone | previous GAAP | D6: InterGlobe_Aviation_Annual_Report_FY2016.pdf
A7: FY2017 | B7: Annual Report FY2017 | C7: Consolidated | Ind AS | D7: InterGlobe_Aviation_Annual_Report_FY2017.pdf
A8: FY2018 | B8: Annual Report FY2018 | C8: Consolidated | Ind AS | D8: InterGlobe_Aviation_Annual_Report_FY2018.pdf
A9: FY2019 | B9: Annual Report FY2019 | C9: Consolidated | Ind AS | D9: InterGlobe_Aviation_Annual_Report_FY2019.pdf
A10: FY2020 | B10: Annual Report FY2020 | C10: Consolidated | Ind AS | D10: InterGlobe_Aviation_Annual_Report_FY2020.pdf
A11: FY2021 | B11: Annual Report FY2021 | C11: Consolidated | Ind AS | D11: InterGlobe_Aviation_Annual_Report_FY2021.pdf
A12: FY2022 | B12: Annual Report FY2022 | C12: Consolidated | Ind AS | D12: InterGlobe_Aviation_Annual_Report_FY2022.pdf
A13: FY2023 | B13: Annual Report FY2023 | C13: Consolidated | Ind AS | D13: InterGlobe_Aviation_Annual_Report_FY2023.pdf
A14: FY2024 | B14: Annual Report FY2024 | C14: Consolidated | Ind AS | D14: InterGlobe_Aviation_Annual_Report_FY2024.pdf
A15: FY2025 | B15: Annual Report FY2025 | C15: Consolidated | Ind AS | D15: InterGlobe_Aviation_Annual_Report_FY2025.pdf
A16: FY2026 | B16: Annual Report FY2026 | C16: Consolidated | Ind AS | D16: InterGlobe_Aviation_Annual_Report_FY2026.pdf
A17: Market Data
A18: 46272 | B18: Screener - InterGlobe Aviation | C18: Market price reference | D18: Screener company page

Sheet 02_Raw_Financials
A1: Historical Financial Statements
A2: InterGlobe Aviation Limited | FY2016-FY2026 | INR crore unless stated
A3: FY2016 is standalone under previous GAAP; FY2017 onward is consolidated under Ind AS. Ind AS 116 was adopted in FY2020.
A5: Metric | B5: Unit | C5: FY2016 | D5: FY2017 | E5: FY2018 | F5: FY2019 | G5: FY2020 | H5: FY2021 | I5: FY2022 | J5: FY2023 | K5: FY2024 | L5: FY2025 | M5: FY2026
A6: Source document | C6: Annual Report FY2016 | D6: Annual Report FY2017 | E6: Annual Report FY2018 | F6: Annual Report FY2019 | G6: Annual Report FY2020 | H6: Annual Report FY2021 | I6: Annual Report FY2022 | J6: Annual Report FY2023 | K6: Annual Report FY2024 | L6: Annual Report FY2025 | M6: FY2026 Audited Consolidated Results
A7: Income Statement
A8: Revenue from operations | B8: INR crore | C8: 16139.909 | D8: 18580.5 | E8: 23020.887 | F8: 28496.772 | G8: 35756.001 | H8: 14640.631 | I8: 25930.927 | J8: 54446.453 | K8: 68904.342 | L8: 80802.9 | M8: 84961.9
A9: Other income | B9: INR crore | C9: 461.393 | D9: 789.07 | E9: 946.856 | F9: 1324.598 | G9: 1535.509 | H9: 1036.964 | I9: 725.598 | J9: 1434.965 | K9: 2326.821 | L9: 3295.3 | M9: 4551.5
A10: Total income | B10: INR crore | C10: =C8+C9 -> 16601.302 | D10: =D8+D9 -> 19369.57 | E10: =E8+E9 -> 23967.743 | F10: =F8+F9 -> 29821.37 | G10: =G8+G9 -> 37291.51 | H10: =H8+H9 -> 15677.595 | I10: =I8+I9 -> 26656.525 | J10: =J8+J9 -> 55881.418 | ... M10: =M8+M9 -> 89513.4
A11: Aircraft fuel expense | B11: INR crore | C11: 4779.324 | D11: 6341.513 | E11: 7760.136 | F11: 11942.793 | G11: 12453.794 | H11: 3831.277 | I11: 9695.236 | J11: 23646.017 | K11: 23904.578 | L11: 26197.3 | M11: 25389.2
A12: Aircraft and engine rentals | B12: INR crore | C12: 2612.152 | D12: 3125.373 | E12: 3610.199 | F12: 4999.449 | G12: 496.657 | H12: 280.457 | I12: 311.684 | J12: 325.84 | K12: 1075.195 | L12: 3010.3 | M12: 2084.7
A13: Supplementary rentals and maintenance | B13: INR crore | G13: 5867.237 | H13: 4191.26 | I13: 6089.784 | J13: 8044.96 | K13: 9931.624 | L13: 11218.5 | M13: 12912.1
A14: Airport fees and charges | B14: INR crore | G14: 2911.684 | H14: 1612.884 | I14: 2286.837 | J14: 3646.8 | K14: 4623.943 | L14: 5753.1 | M14: 6548.2
A15: Purchase of stock-in-trade | B15: INR crore | C15: 114.782 | D15: 123.832 | E15: 123.876 | F15: 139.795 | G15: 180.908 | H15: 54.321 | I15: 118.142 | J15: 287.244 | K15: 336.861 | L15: 383.4 | M15: 496.3
A16: Change in inventories | B16: INR crore | C16: -1.132 | D16: -0.294 | E16: 1.265 | F16: -0.655 | G16: -3.053 | H16: 1.161 | I16: -1.677 | J16: -1.244 | K16: 5.41 | L16: -0.2 | M16: -1.4
A17: Employee expense | B17: INR crore | C17: 1789.923 | D17: 2048.19 | E17: 2455.022 | F17: 3210.557 | G17: 4709.959 | H17: 3295.492 | I17: 3486.443 | J17: 4794.752 | K17: 6461.856 | L17: 7472.5 | M17: 8272.2
A18: Foreign exchange loss (net) | B18: INR crore | F18: 467.487 | G18: 1546.189 | H18: -523.026 | I18: 940.838 | J18: 2959.773 | K18: 717.397 | L18: 1617.9 | M18: 8975.7
A19: Other expenses | B19: INR crore | C19: 3839.371 | D19: 4798.624 | E19: 6113.926 | F19: 7940.779 | G19: 3534.004 | H19: 1910.41 | I19: 2456.307 | J19: 4246.961 | K19: 5529.907 | L19: 7091.8 | M19: 8301.5
A20: Depreciation and amortisation | B20: INR crore | C20: 503.079 | D20: 457.253 | E20: 436.877 | F20: 759.58 | G20: 3973.929 | H20: 4699.446 | I20: 5068.6 | J20: 5102.969 | K20: 6425.729 | L20: 8680.2 | M20: 10808.2
A21: Finance costs | B21: INR crore | C21: 134.853 | D21: 330.78 | E21: 339.815 | F21: 508.963 | G21: 1875.871 | H21: 2141.983 | I21: 2358.015 | J21: 3131.731 | K21: 4169.354 | L21: 5080 | M21: 5890.8
A22: Total expenses | B22: INR crore | C22: 13772.352 | D22: 17225.271 | E22: 20841.116 | F22: 29968.748 | G22: 37547.179 | H22: 21495.665 | I22: 32810.209 | J22: 56185.803 | K22: 63181.854 | L22: 76504.8 | M22: 89677.5
A23: Exceptional items | B23: INR crore | M23: 1796.4
A24: Profit before tax | B24: INR crore | C24: 2828.95 | D24: 2144.299 | E24: 3126.627 | F24: -147.378 | G24: -255.669 | H24: -5818.07 | I24: -6153.684 | J24: -304.385 | K24: 8049.309 | L24: 7593.4 | M24: -1960.5
A25: Total tax expense / (credit) | B25: INR crore | C25: 839.23 | D25: 485.152 | E25: 884.303 | F25: -304.625 | G25: -21.991 | H25: -11.643 | I25: 8.161 | J25: 1.404 | K25: -123.159 | L25: 335 | M25: 433.1
A26: Profit after tax | B26: INR crore | C26: 1989.72 | D26: 1659.147 | E26: 2242.324 | F26: 157.247 | G26: -233.678 | H26: -5806.427 | I26: -6161.845 | J26: -305.789 | K26: 8172.468 | L26: 7258.4 | M26: -2393.6
A27: Basic EPS | B27: INR per share | C27: 58.17 | D27: 45.94 | E27: 60.03 | F27: 4.09 | G27: -6.07 | H27: -150.89 | I27: -160.01 | J27: -7.93 | K27: 211.84 | L27: 187.93 | M27: -61.88
A28: Diluted EPS | B28: INR per share | C28: 56.49 | D28: 45.85 | E28: 59.9 | F28: 4.09 | G28: -6.07 | H28: -150.89 | I28: -160.01 | J28: -7.93 | K28: 211.61 | L28: 187.67 | M28: -61.88
A29: Total expense check | B29: INR crore | C29: =SUM(C11:C21)-C22 -> 0 | D29: =SUM(D11:D21)-D22 -> 0 | E29: =SUM(E11:E21)-E22 -> 0 | F29: =SUM(F11:F21)-F22 -> 0 | G29: =SUM(G11:G21)-G22 -> 0 | H29: =SUM(H11:H21)-H22 -> 0 | I29: =SUM(I11:I21)-I22 -> 0 | J29: =SUM(J11:J21)-J22 -> 0 | ... M29: =SUM(M11:M21)-M22 -> 0
A30: P&L check | B30: INR crore | C30: =C10-C22-C23-C24 -> 0 | D30: =D10-D22-D23-D24 -> 0 | E30: =E10-E22-E23-E24 -> 0 | F30: =F10-F22-F23-F24 -> -4.2632564e-12 | G30: =G10-G22-G23-G24 -> 5.5990768e-12 | H30: =H10-H22-H23-H24 -> 0 | I30: =I10-I22-I23-I24 -> 0 | J30: =J10-J22-J23-J24 -> -2.0463631e-12 | ... M30: =M10-M22-M23-M24 -> -5.9117156e-12
A32: Balance Sheet
A33: Property, plant and equipment | B33: INR crore | C33: 4675.515 | D33: 3747.472 | E33: 4534.756 | F33: 5631.554 | G33: 2499.569 | H33: 796.966 | I33: 823.953 | J33: 1111.169 | K33: 1902.912 | L33: 2677.9 | M33: 11087.1
A34: Right-of-use assets | B34: INR crore | C34: 0 | D34: 0 | E34: 0 | F34: 0 | G34: 14246.138 | H34: 17986.171 | I34: 20438.148 | J34: 26536.495 | K34: 34202.308 | L34: 49073.9 | M34: 52054
A35: Capital work-in-progress | B35: INR crore | C35: 23.734 | D35: 23.303 | E35: 29.42 | F35: 22.015 | G35: 129.27 | H35: 66.351 | I35: 119.318 | J35: 0 | K35: 0.143 | L35: 0.7 | M35: 38.7
A36: Intangible assets | B36: INR crore | C36: 19.974 | D36: 46.369 | E36: 44.053 | F36: 30.488 | G36: 33.591 | H36: 33.496 | I36: 21.562 | J36: 10.727 | K36: 48.327 | L36: 29.9 | M36: 16
A37: Intangible assets under development | B37: INR crore | C37: 8.231 | D37: 1.883 | E37: 3.07 | F37: 1.614 | G37: 10.969 | H37: 5.419 | I37: 6.039 | J37: 20.817 | K37: 1.339 | L37: 2.3 | M37: 20.6
A38: Non-current investments | B38: INR crore | C38: 0.025 | D38: 0.018 | E38: 0.017 | F38: 0.015 | G38: 0.075 | H38: 0.083 | I38: 0.012 | J38: 0.068 | K38: 974.839 | L38: 1318.3 | M38: 1931
A39: Non-current loans | B39: INR crore | C39: 1193.062 | D39: 544.026 | E39: 683.134 | F39: 584.397 | G39: 1275.954 | H39: 1580.657 | I39: 0 | J39: 0 | K39: 0 | L39: 0 | M39: 0
A40: Non-current other financial assets | B40: INR crore | C40: 0 | D40: 1035.639 | E40: 819.522 | F40: 198.821 | G40: 5.83 | H40: 1.634 | I40: 2091.122 | J40: 2449.966 | K40: 5296.216 | L40: 7493.3 | M40: 7110.7
A41: Deferred tax assets | B41: INR crore | C41: 0 | D41: 0 | E41: 0 | F41: 0.967 | G41: 299.282 | H41: 302.693 | I41: 294.944 | J41: 294.944 | K41: 419.188 | L41: 419.2 | M41: 0
A42: Income tax assets | B42: INR crore | C42: 0 | D42: 9.76 | E42: 38.639 | F42: 124.049 | G42: 429.671 | H42: 513.953 | I42: 711.922 | J42: 1099.787 | K42: 1610.098 | L42: 1708 | M42: 1977.5
A43: Other non-current assets | B43: INR crore | C43: 1497.784 | D43: 354.874 | E43: 345.122 | F43: 315.876 | G43: 714.269 | H43: 949.813 | I43: 1226.699 | J43: 1497.132 | K43: 1916.03 | L43: 2416.9 | M43: 3837.3
A44: Total non-current assets | B44: INR crore | C44: =SUM(C33:C43) -> 7418.325 | D44: =SUM(D33:D43) -> 5763.344 | E44: =SUM(E33:E43) -> 6497.733 | F44: =SUM(F33:F43) -> 6909.796 | G44: =SUM(G33:G43) -> 19644.618 | H44: =SUM(H33:H43) -> 22237.236 | I44: =SUM(I33:I43) -> 25733.719 | J44: =SUM(J33:J43) -> 33021.105 | ... M44: =SUM(M33:M43) -> 78072.9
A45: Inventories | B45: INR crore | C45: 126.72 | D45: 163.15 | E45: 183.227 | F45: 211.441 | G45: 286.128 | H45: 316.418 | I45: 408.063 | J45: 591.067 | K45: 624.798 | L45: 820.3 | M45: 984.8
A46: Current investments | B46: INR crore | C46: 974.12 | D46: 3713.41 | E46: 6343.912 | F46: 6516.57 | G46: 9499.167 | H46: 7339.406 | I46: 8106.472 | J46: 11558.029 | K46: 15571.123 | L46: 24774.8 | M46: 25743.8
A47: Trade receivables | B47: INR crore | C47: 157.114 | D47: 158.702 | E47: 226.315 | F47: 362.467 | G47: 259.416 | H47: 218.978 | I47: 332.923 | J47: 519.904 | K47: 642.523 | L47: 739.7 | M47: 599.6
A48: Cash and cash equivalents | B48: INR crore | C48: 805.368 | D48: 153.119 | E48: 670.718 | F48: 728.417 | G48: 719.066 | H48: 508.885 | I48: 1015.329 | J48: 1267.969 | K48: 695.277 | L48: 1073.1 | M48: 1323.9
A49: Other bank balances | B49: INR crore | C49: 2913.302 | D49: 4479.426 | E49: 5909.973 | F49: 7893.58 | G49: 10153.364 | H49: 10718.78 | I49: 9104.812 | J49: 10571.716 | K49: 16025.33 | L49: 17889.8 | M49: 22675.4
A50: Current loans | B50: INR crore | C50: 224.875 | D50: 3.976 | E50: 191.495 | F50: 466.961 | G50: 455.123 | H50: 128.604 | I50: 0 | J50: 0 | K50: 0 | L50: 0 | M50: 0
A51: Current other financial assets | B51: INR crore | C51: 0 | D51: 410.086 | E51: 458.001 | F51: 792.52 | G51: 623.127 | H51: 619.286 | I51: 328.11 | J51: 1039.767 | K51: 1728.191 | L51: 3586.7 | M51: 4794.7
A52: Other current assets | B52: INR crore | C52: 399.287 | D52: 364.523 | E52: 647.922 | F52: 1145.09 | G52: 461.069 | H52: 818.216 | I52: 933.17 | J52: 600.262 | K52: 565.875 | L52: 1818.7 | M52: 1807
A53: Total current assets | B53: INR crore | C53: =SUM(C45:C52) -> 5600.786 | D53: =SUM(D45:D52) -> 9446.392 | E53: =SUM(E45:E52) -> 14631.563 | F53: =SUM(F45:F52) -> 18117.046 | G53: =SUM(G45:G52) -> 22456.46 | H53: =SUM(H45:H52) -> 20668.573 | I53: =SUM(I45:I52) -> 20228.879 | J53: =SUM(J45:J52) -> 26148.714 | ... M53: =SUM(M45:M52) -> 57929.2
A54: Assets held for sale | B54: INR crore | C54: 0 | D54: 0 | E54: 0 | F54: 0 | G54: 0 | H54: 145.344 | I54: 0 | J54: 0 | K54: 0 | L54: 0 | M54: 0
A55: Total assets | B55: INR crore | C55: =C44+C53+C54 -> 13019.111 | D55: =D44+D53+D54 -> 15209.736 | E55: =E44+E53+E54 -> 21129.296 | F55: =F44+F53+F54 -> 25026.842 | G55: =G44+G53+G54 -> 42101.078 | H55: =H44+H53+H54 -> 43051.153 | I55: =I44+I53+I54 -> 45962.598 | J55: =J44+J53+J54 -> 59169.819 | ... M55: =M44+M53+M54 -> 136002.1
A56: Share capital | B56: INR crore | C56: 360.357 | D56: 361.468 | E56: 384.407 | F56: 384.407 | G56: 384.796 | H56: 384.91 | I56: 385.255 | J56: 385.547 | K56: 385.979 | L56: 386.4 | M56: 386.6
A57: Other equity | B57: INR crore | C57: 1473.92 | D57: 3417.708 | E57: 6692.948 | F57: 6561.403 | G57: 5493.144 | H57: -274.051 | I57: -6373.317 | J57: -6632.063 | K57: 1610.453 | L57: 8981.8 | M57: 6584.5
A58: Total equity (including NCI) | B58: INR crore | C58: 1834.277 | D58: 3779.176 | E58: 7077.355 | F58: 6945.81 | G58: 5877.94 | H58: 110.859 | I58: -5988.062 | J58: -6246.516 | K58: 1996.432 | L58: 9368.2 | M58: 6987.4
A59: Non-current borrowings | B59: INR crore | C59: 2949.861 | D59: 2395.708 | E59: 2241.37 | F59: 2193.669 | G59: 346.587 | H59: 381.628 | I59: 416.171 | J59: 0 | K59: 0 | L59: 0 | M59: 0
A60: Non-current lease liabilities | B60: INR crore | C60: 0 | D60: 0 | E60: 0 | F60: 0 | G60: 15579.101 | H60: 20280.534 | I60: 25058.659 | J60: 32224.609 | K60: 37863.462 | L60: 54668.3 | M60: 64470.5
A61: Non-current other financial liabilities | B61: INR crore | C61: 2472.247 | D61: 2268.534 | E61: 2995.908 | F61: 3387.894 | G61: 3038.886 | H61: 2604.929 | I61: 3309.3 | J61: 7881.11 | K61: 9234.267 | L61: 15119.2 | M61: 22911.1
A62: Non-current provisions | B62: INR crore | C62: 81.064 | D62: 122.394 | E62: 196.893 | F62: 275.82 | G62: 563.498 | H62: 552.294 | I62: 589.688 | J62: 1336.454 | K62: 2230.112 | L62: 2407.9 | M62: 3310
A63: Deferred tax liabilities | B63: INR crore | C63: 517.972 | D63: 161.806 | E63: 369.525 | F63: 64.416 | G63: 0 | H63: 0 | I63: 0 | J63: 0 | K63: 0 | L63: 0 | M63: 0
A64: Non-current deferred incentives | B64: INR crore | C64: 1177.816 | D64: 1689.99 | E64: 2057.819 | F64: 4114.359 | G64: 220.631 | H64: 173.027 | I64: 125.423 | J64: 77.819 | K64: 30.22 | L64: 4.8 | M64: 0
A65: Other non-current liabilities | B65: INR crore | C65: 0 | D65: 7.5 | E65: 67.393 | F65: 34.518 | G65: 36.977 | H65: 24.19 | I65: 34.279 | J65: 45.197 | K65: 71.706 | L65: 57.3 | M65: 52.1
A66: Total non-current liabilities | B66: INR crore | C66: =SUM(C59:C65) -> 7198.96 | D66: =SUM(D59:D65) -> 6645.932 | E66: =SUM(E59:E65) -> 7928.908 | F66: =SUM(F59:F65) -> 10070.676 | G66: =SUM(G59:G65) -> 19785.68 | H66: =SUM(H59:H65) -> 24016.602 | I66: =SUM(I59:I65) -> 29533.52 | J66: =SUM(J59:J65) -> 41565.189 | ... M66: =SUM(M59:M65) -> 90743.7
A67: Current borrowings | B67: INR crore | C67: 0 | D67: 0 | E67: 0 | F67: 0 | G67: 0 | H67: 2123.995 | I67: 3480.565 | J67: 2252.337 | K67: 1891.707 | L67: 1800 | M67: 1806.3
A68: Current lease liabilities | B68: INR crore | C68: 0 | D68: 0 | E68: 0 | F68: 0 | G68: 6454.427 | H68: 7073.497 | I68: 7922.442 | J68: 10377.267 | K68: 11524.851 | L68: 10341.5 | M68: 11472.4
A69: Trade payables - MSME | B69: INR crore | C69: 1.589 | D69: 0 | E69: 0 | F69: 4.79 | G69: 6.115 | H69: 28.098 | I69: 9.74 | J69: 19.961 | K69: 26.659 | L69: 33.1 | M69: 60.7
A70: Trade payables - other | B70: INR crore | C70: 739.639 | D70: 774.61 | E70: 1000.201 | F70: 1448.018 | G70: 1561.467 | H70: 1523.231 | I70: 3142.08 | J70: 3189.028 | K70: 3130.956 | L70: 4142.5 | M70: 4929.8
A71: Current other financial liabilities | B71: INR crore | C71: 0 | D71: 1432.267 | E71: 1547.283 | F71: 2123.048 | G71: 4589.739 | H71: 4723.46 | I71: 3692.859 | J71: 2590.159 | K71: 7050.992 | L71: 7752.3 | M71: 8606
A72: Current provisions | B72: INR crore | C72: 688.318 | D72: 66.706 | E72: 103.246 | F72: 163.832 | G72: 1396.254 | H72: 1608.358 | I72: 760.276 | J72: 289.65 | K72: 588.972 | L72: 1746.8 | M72: 2621
A73: Current tax liabilities | B73: INR crore | C73: 0 | D73: 44.677 | E73: 12.751 | F73: 3.351 | G73: 3.076 | H73: 3.076 | I73: 3.076 | J73: 3.076 | K73: 3.076 | L73: 3.1 | M73: 4.3
A74: Current deferred incentives | B74: INR crore | C74: 405.407 | D74: 493.783 | E74: 543.88 | F74: 1073.915 | G74: 47.605 | H74: 47.603 | I74: 47.604 | J74: 47.604 | K74: 47.599 | L74: 25.8 | M74: 0
A75: Other current liabilities | B75: INR crore | C75: 2150.921 | D75: 1972.585 | E75: 2915.672 | F75: 3193.402 | G75: 2378.775 | H75: 1792.374 | I75: 3358.498 | J75: 5082.064 | K75: 6533.506 | L75: 8372.7 | M75: 8770.5
A76: Total current liabilities | B76: INR crore | C76: =SUM(C67:C75) -> 3985.874 | D76: =SUM(D67:D75) -> 4784.628 | E76: =SUM(E67:E75) -> 6123.033 | F76: =SUM(F67:F75) -> 8010.356 | G76: =SUM(G67:G75) -> 16437.458 | H76: =SUM(H67:H75) -> 18923.692 | I76: =SUM(I67:I75) -> 22417.14 | J76: =SUM(J67:J75) -> 23851.146 | ... M76: =SUM(M67:M75) -> 38271
A77: Total equity and liabilities | B77: INR crore | C77: =C58+C66+C76 -> 13019.111 | D77: =D58+D66+D76 -> 15209.736 | E77: =E58+E66+E76 -> 21129.296 | F77: =F58+F66+F76 -> 25026.842 | G77: =G58+G66+G76 -> 42101.078 | H77: =H58+H66+H76 -> 43051.153 | I77: =I58+I66+I76 -> 45962.598 | J77: =J58+J66+J76 -> 59169.819 | ... M77: =M58+M66+M76 -> 136002.1
A79: Balance sheet check | B79: INR crore | C79: =C55-C77 -> 0 | D79: =D55-D77 -> 0 | E79: =E55-E77 -> 0 | F79: =F55-F77 -> 0 | G79: =G55-G77 -> 0 | H79: =H55-H77 -> 0 | I79: =I55-I77 -> 0 | J79: =J55-J77 -> 0 | ... M79: =M55-M77 -> 0
A81: Cash Flow Statement
A82: Profit before tax | B82: INR crore | C82: 2828.95 | D82: 2144.299 | E82: 3126.627 | G82: -255.669 | H82: -5818.07 | I82: -6153.684 | J82: -304.385 | K82: 8049.309 | L82: 7593.4 | M82: -1960.5
A83: Depreciation and amortisation | B83: INR crore | C83: 503.079 | D83: 457.253 | E83: 436.877 | F83: 759.58 | G83: 3973.929 | H83: 4699.446 | I83: 5068.6 | J83: 5102.969 | K83: 6425.729 | L83: 8680.2 | M83: 10808.2
A84: Finance costs | B84: INR crore | C84: 134.853 | D84: 330.78 | E84: 339.815 | F84: 508.963 | G84: 1875.871 | H84: 2141.983 | I84: 2358.015 | J84: 3131.731 | K84: 4169.354 | L84: 5080 | M84: 5890.8
A85: Interest income | B85: INR crore | C85: -368.741 | D85: -391.327 | E85: -400.805 | F85: -434.411 | G85: -257.17 | H85: -126.928 | I85: -67.525 | J85: -269.756 | K85: -846.455 | L85: -1121.8 | M85: -1306.6
A86: Unrealised foreign exchange | B86: INR crore | C86: 205.793 | D86: -86.18 | E86: 9.976 | F86: 354.606 | G86: 1312.227 | H86: -466.475 | I86: 788.601 | J86: 3003.537 | K86: 826.151 | L86: 1708.3 | M86: 9318.6
A87: Operating profit before working capital changes | B87: INR crore | C87: 3325.502 | D87: 2092.647 | E87: 3130.909 | F87: 377.848 | G87: 5676.597 | J87: 9984.564 | K87: 17378.749 | L87: 20066.1 | M87: 21679.4
A88: Change in net working capital | B88: INR crore | C88: =C89-C87 -> 349.689 | D88: =D89-D87 -> 2113.519 | E88: =E89-E87 -> 1509.697 | F88: =F89-F87 -> 2894.027 | G88: =G89-G87 -> 1610.211 | H88: =H89-H87 -> 0 | I88: =I89-I87 -> 0 | J88: =J89-J87 -> 3132.644 | ... M88: =M89-M87 -> 2047.3
A89: Cash generated from operations | B89: INR crore | C89: 3675.191 | D89: 4206.166 | E89: 4640.606 | F89: 3271.875 | G89: 7286.808 | J89: 13117.208 | K89: 21728.971 | L89: 24583.8 | M89: 23726.7
A90: Income taxes paid | B90: INR crore | C90: -576.116 | D90: -424.096 | E90: -737.522 | F90: -96.334 | G90: -315.026 | H90: -76.414 | I90: -198.381 | J90: -389.269 | K90: -511.396 | L90: -432.5 | M90: -256.8
A91: Net cash from operating activities | B91: INR crore | C91: 3099.075 | D91: 3782.07 | E91: 3903.084 | F91: 3175.541 | G91: 6971.782 | H91: -1614.154 | I91: 2090.578 | J91: 12727.939 | K91: 21217.575 | L91: 24151.3 | M91: 23469.9
A92: Capital expenditure | B92: INR crore | C92: -231.99 | D92: -237.238 | E92: -1220.215 | F92: -1711.562 | G92: -1088.306 | H92: -436.887 | I92: -346.881 | J92: -569.804 | K92: -1102.645 | L92: -1604.8 | M92: -2271.8
A93: Basic free cash flow | B93: INR crore | C93: =C91+C92 -> 2867.085 | D93: =D91+D92 -> 3544.832 | E93: =E91+E92 -> 2682.869 | F93: =F91+F92 -> 1463.979 | G93: =G91+G92 -> 5883.476 | H93: =H91+H92 -> -2051.041 | I93: =I91+I92 -> 1743.697 | J93: =J91+J92 -> 12158.135 | ... M93: =M91+M92 -> 21198.1
A94: Asset sale proceeds | B94: INR crore | C94: 0.162 | D94: 613.23 | E94: 0.243 | F94: 5.407 | G94: 26.738 | H94: 16.469 | I94: 6.665 | J94: 4.39 | K94: 5.102 | L94: 11.9 | M94: 7.1
A95: Interest received | B95: INR crore | C95: 328.58 | D95: 346.024 | E95: 531.045 | F95: 500.876 | G95: 369.297 | H95: 136.692 | I95: 91.55 | J95: 156.831 | K95: 575.839 | L95: 1132 | M95: 1352.6
A96: Other investing flows | B96: INR crore | C96: =C97-C92-C94-C95 -> -1422.946 | D96: =D97-D92-D94-D95 -> -3759.873 | E96: =E97-E92-E94-E95 -> -3470.606 | F96: =F97-F92-F94-F95 -> -1330.772 | G96: =G97-G92-G94-G95 -> -3875.727 | H96: =H97-H92-H94-H95 -> 3480.764 | I96: =I97-I92-I94-I95 -> 1751.117 | J96: =J97-J92-J94-J95 -> -3650.905 | ... M96: =M97-M92-M94-M95 -> -1040.4
A97: Net cash from investing activities | B97: INR crore | C97: -1326.194 | D97: -3037.857 | E97: -4159.533 | F97: -2536.051 | G97: -4567.998 | H97: 3197.038 | I97: 1502.451 | J97: -4059.488 | K97: -11808.991 | L97: -12759.3 | M97: -1952.5
A98: Borrowing proceeds | B98: INR crore | C98: 84.37 | D98: 67.661 | E98: 44.977 | F98: 48.354 | G98: 42.061 | H98: 4844.204 | I98: 15235.854 | J98: 9833.244 | K98: 7201.47 | L98: 1800 | M98: 6.3
A99: Borrowing repayments | B99: INR crore | C99: -1108.49 | D99: -752.639 | E99: -232.881 | F99: -256.193 | G99: 0 | H99: -3009.991 | I99: -13864.522 | J99: -11505.877 | K99: -7483.422 | L99: -1891.7 | M99: 0
A100: Lease payments | B100: INR crore | C100: -70.157 | D100: -47.879 | E100: -53.341 | F100: -77.009 | G100: 0 | H100: 0 | I100: 0 | J100: 0 | K100: 0 | L100: 0 | M100: -16180.2
A101: Interest paid | B101: INR crore | C101: -12.376 | D101: -16.877 | E101: -20.92 | F101: -29.265 | G101: -34.01 | H101: -29.204 | I101: -45.671 | J101: -34.457 | K101: -60.761 | L101: -26 | M101: -4737.3
A102: Dividends paid | B102: INR crore | C102: -1102.649 | D102: -542.203 | E102: 0 | F102: 0 | G102: 0 | H102: 0 | I102: 0 | J102: 0 | K102: 0 | L102: 0 | M102: -386.5
A103: Equity issuance | B103: INR crore | C103: 1213.815 | D103: 0 | E103: 0 | F103: 0 | G103: 0 | H103: 0 | I103: 0 | J103: 0 | K103: 0 | L103: 0 | M103: 0
A104: Other financing flows | B104: INR crore | C104: =C105-SUM(C98:C103) -> -224.477 | D104: =D105-SUM(D98:D103) -> -109.269 | E104: =E105-SUM(E98:E103) -> 1028.12 | F104: =F105-SUM(F98:F103) -> -278.045 | G104: =G105-SUM(G98:G103) -> -2415.535 | H104: =H105-SUM(H98:H103) -> -3580.346 | I104: =I105-SUM(I98:I103) -> -4413.503 | J104: =J105-SUM(J98:J103) -> -6725.37 | ... M104: =M105-SUM(M98:M103) -> 21.6
...

Sheet 03_Raw_Operating_KPIs
A1: Historical Operating KPIs
A2: InterGlobe Aviation Limited | FY2016-FY2026
A3: Company full-year disclosures. Later-year traffic metrics include non-scheduled operations where stated.
A5: Metric | B5: Unit | C5: FY2016 | D5: FY2017 | E5: FY2018 | F5: FY2019 | G5: FY2020 | H5: FY2021 | I5: FY2022 | J5: FY2023 | K5: FY2024 | L5: FY2025 | M5: FY2026
A6: Source document | C6: FY2016 AR / FY2017 Q4 | D6: FY2017 Q4 / AR | E6: FY2018 Q4 / AR | F6: FY2019 Q4 / AR | G6: FY2020 Q4 / AR | H6: FY2021 Q4 / AR | I6: FY2022 Q4 / AR | J6: FY2023 Q4 / AR | K6: FY2024 Q4 / AR | L6: FY2025 Q4 / AR | M6: FY2026 Q4 / AR
A8: Traffic and Capacity
A9: ASK (available seat km) | B9: billion | C9: 42.83 | D9: 54.58 | E9: 63.5 | F9: 81 | G9: 96.2 | H9: 45.4 | I9: 70.4 | J9: 114.4 | K9: 139.3 | L9: 157.5 | M9: 172.4
A10: RPK (revenue passengers km) | B10: billion | C10: 35.97 | D10: 46.29 | E10: 55.5 | F10: 69.8 | G10: 82.5 | H10: 31.5 | I10: 51.8 | J10: 93.9 | K10: 119.7 | L10: 135.4 | M10: 145.5
A11: Load factor | B11: % | C11: =C10/C9 -> 0.83983189 | D11: =D10/D9 -> 0.84811286 | E11: =E10/E9 -> 0.87401575 | F11: =F10/F9 -> 0.8617284 | G11: =G10/G9 -> 0.85758836 | H11: =H10/H9 -> 0.6938326 | I11: =I10/I9 -> 0.73579545 | J11: =J10/J9 -> 0.8208042 | ... M11: =M10/M9 -> 0.84396752
A12: Passengers | B12: million | C12: 33.104 | D12: 43.532 | E12: 52.142 | F12: 64.743 | G12: 75.026 | H12: 30.7 | I12: 49.8 | J12: 85.6 | K12: 106.7 | L12: 118.6 | M12: 123.4
A14: Unit Revenue and Cost
A15: Yield | B15: INR / passenger km | C15: 3.91 | D15: 3.5 | E15: 3.59 | F15: 3.6 | G15: 3.81 | H15: 3.76 | I15: 4.24 | J15: 5.13 | K15: 5.08 | L15: 5.15 | M15: 5.06
A16: RASK | B16: INR / ASK | C16: 3.78 | D16: 3.44 | E16: 3.64 | F16: 3.57 | G16: 3.77 | H16: 3.3 | I16: 3.73 | J16: 4.8 | K16: 4.96 | L16: 5.14 | M16: 4.99
A17: CASK | B17: INR / ASK | C17: 3.12 | D17: 3.04 | E17: 3.15 | F17: 3.59 | G17: 3.8 | H17: 4.58 | I17: 4.6 | J17: 4.83 | K17: 4.38 | L17: 4.66 | M17: 5
A18: Ex-fuel CASK | B18: INR / ASK | C18: 2.01 | D18: 1.88 | E18: 1.93 | F18: 2.11 | G18: 2.5 | H18: 3.74 | I18: 3.22 | J18: 2.76 | K18: 2.66 | L18: 3 | M18: 3.52
A19: Fuel CASK | B19: INR / ASK | C19: =C17-C18 -> 1.11 | D19: =D17-D18 -> 1.16 | E19: =E17-E18 -> 1.22 | F19: =F17-F18 -> 1.48 | G19: =G17-G18 -> 1.3 | H19: =H17-H18 -> 0.84 | I19: =I17-I18 -> 1.38 | J19: =J17-J18 -> 2.07 | ... M19: =M17-M18 -> 1.48
A21: Network and Fleet
A22: Closing fleet | B22: aircraft | C22: 107 | D22: 131 | E22: 159 | F22: 217 | G22: 262 | H22: 285 | I22: 275 | J22: 304 | K22: 367 | L22: 434 | M22: 441
A23: Net fleet additions | B23: aircraft | D23: =D22-C22 -> 24 | E23: =E22-D22 -> 28 | F23: =F22-E22 -> 58 | G23: =G22-F22 -> 45 | H23: =H22-G22 -> 23 | I23: =I22-H22 -> -10 | J23: =J22-I22 -> 29 | K23: =K22-J22 -> 63 | ... M23: =M22-L22 -> 7
A24: Peak daily flights | B24: flights | C24: 731 | D24: 896 | E24: 1086 | F24: 1376 | G24: 1674 | H24: 1301 | I24: 1577 | J24: 1815 | K24: 2021 | L24: 2304 | M24: 2241
A25: Domestic destinations | B25: destinations | C25: 35 | D25: 38 | E25: 42 | F25: 52 | G25: 62 | H25: 65 | I25: 73 | J25: 78 | K25: 88 | L25: 91 | M25: 97
A26: International destinations | B26: destinations | C26: 5 | D26: 6 | E26: 8 | F26: 16 | G26: 24 | H26: 10 | I26: 15 | J26: 22 | K26: 30 | L26: 40 | M26: 45
A27: Total destinations | B27: destinations | C27: =C25+C26 -> 40 | D27: =D25+D26 -> 44 | E27: =E25+E26 -> 50 | F27: =F25+F26 -> 68 | G27: =G25+G26 -> 86 | H27: =H25+H26 -> 75 | I27: =I25+I26 -> 88 | J27: =J25+J26 -> 100 | ... M27: =M25+M26 -> 142

Sheet 04_Industry_Data
A1: Indian Aviation Industry Context
A2: External demand and market-position benchmarks supporting capacity assumptions
A3: Calendar-year industry data is shown separately from IndiGo fiscal-year forecasts.
A5: Metric | B5: Unit | C5: 2023A | D5: 2024A | E5: 2025A | F5: Source / read-across
A8: Industry Traffic
A9: Total passengers at Indian airports | B9: million | C9: 369.85 | D9: 400.95 | E9: 420.03 | F9: Ministry of Civil Aviation annual reports
A10: Growth | B10: % | D10: =D9/C9-1 -> 0.084088144 | E10: =E9/D9-1 -> 0.047586981
A11: Domestic passengers at Indian airports | B11: million | C11: 302.92 | D11: 325.49 | E11: 338.91 | F11: Ministry of Civil Aviation annual reports
A12: Growth | B12: % | D12: =D11/C11-1 -> 0.074508121 | E12: =E11/D11-1 -> 0.041230145
A13: Total aircraft movements | B13: 000 movements | C13: 2656.43 | D13: 2815.55 | E13: 2899.5 | F13: Ministry of Civil Aviation annual reports
A14: Growth | B14: % | D14: =D13/C13-1 -> 0.059899941 | E14: =E13/D13-1 -> 0.029816554
A16: Market Position
A17: IndiGo domestic market share | B17: % | E17: 0.642 | F17: DGCA data, August 2025
A19: Model Read-Across
A20: FY2027E ASK growth | B20: % | E20: ='06_Operating_Model'!F19 -> 0.044571429
A21: FY2027E passenger growth | B21: % | E21: ='06_Operating_Model'!F29 -> 0.031409589
A22: Interpretation | C22: Recent industry passenger growth is 4.8%; FY2027E capacity growth of 4.5% is broadly aligned with recent demand growth.
A24: Sources | C24: Ministry of Civil Aviation annual reports for 2024-25 and 2025; IndiGo October 2025 newsletter citing DGCA.

Sheet 05_Historical_Analysis
A1: Historical Analysis
A2: InterGlobe Aviation Limited | FY2016-FY2026
A3: Historical calculations linked to reported financial statements and operating KPIs. FY2020 is the Ind AS 116 accounting break; pre-FY2020 and post-FY2020 lease-based returns are not directly comparable.
A5: Metric | B5: Unit | C5: FY2016 | D5: FY2017 | E5: FY2018 | F5: FY2019 | G5: FY2020 | H5: FY2021 | I5: FY2022 | J5: FY2023 | K5: FY2024 | L5: FY2025 | M5: FY2026
A6: Operating period | C6: Pre-COVID | D6: Pre-COVID | E6: Pre-COVID | F6: Pre-COVID | G6: Ind AS 116 transition | H6: COVID disruption | I6: COVID disruption | J6: Recovery | K6: Normalized recent | L6: Normalized recent | M6: Recent / FX-distorted
A8: Growth and Network Expansion
A9: Revenue growth | B9: % | D9: =IFERROR(D58/C58-1,"") -> 0.15121467 | E9: =IFERROR(E58/D58-1,"") -> 0.23898103 | F9: =IFERROR(F58/E58-1,"") -> 0.23786594 | G9: =IFERROR(G58/F58-1,"") -> 0.25473864 | H9: =IFERROR(H58/G58-1,"") -> -0.59054059 | I9: =IFERROR(I58/H58-1,"") -> 0.77116184 | J9: =IFERROR(J58/I58-1,"") -> 1.0996724 | K9: =IFERROR(K58/J58-1,"") -> 0.26554327 | ... M9: =IFERROR(M58/L58-1,"") -> 0.051470925
A10: Passenger growth | B10: % | D10: =IFERROR(D89/C89-1,"") -> 0.31500725 | E10: =IFERROR(E89/D89-1,"") -> 0.19778554 | F10: =IFERROR(F89/E89-1,"") -> 0.24166699 | G10: =IFERROR(G89/F89-1,"") -> 0.15882798 | H10: =IFERROR(H89/G89-1,"") -> -0.59080852 | I10: =IFERROR(I89/H89-1,"") -> 0.62214984 | J10: =IFERROR(J89/I89-1,"") -> 0.7188755 | K10: =IFERROR(K89/J89-1,"") -> 0.24649533 | ... M10: =IFERROR(M89/L89-1,"") -> 0.040472175
A11: ASK growth | B11: % | D11: =IFERROR(D87/C87-1,"") -> 0.27434042 | E11: =IFERROR(E87/D87-1,"") -> 0.16342983 | F11: =IFERROR(F87/E87-1,"") -> 0.27559055 | G11: =IFERROR(G87/F87-1,"") -> 0.18765432 | H11: =IFERROR(H87/G87-1,"") -> -0.52806653 | I11: =IFERROR(I87/H87-1,"") -> 0.55066079 | J11: =IFERROR(J87/I87-1,"") -> 0.625 | K11: =IFERROR(K87/J87-1,"") -> 0.21765734 | ... M11: =IFERROR(M87/L87-1,"") -> 0.094603175
A12: RPK growth | B12: % | D12: =IFERROR(D88/C88-1,"") -> 0.28690575 | E12: =IFERROR(E88/D88-1,"") -> 0.19896306 | F12: =IFERROR(F88/E88-1,"") -> 0.25765766 | G12: =IFERROR(G88/F88-1,"") -> 0.18194842 | H12: =IFERROR(H88/G88-1,"") -> -0.61818182 | I12: =IFERROR(I88/H88-1,"") -> 0.64444444 | J12: =IFERROR(J88/I88-1,"") -> 0.81274131 | K12: =IFERROR(K88/J88-1,"") -> 0.27476038 | ... M12: =IFERROR(M88/L88-1,"") -> 0.074593796
A13: Fleet growth | B13: % | D13: =IFERROR(D90/C90-1,"") -> 0.22429907 | E13: =IFERROR(E90/D90-1,"") -> 0.21374046 | F13: =IFERROR(F90/E90-1,"") -> 0.36477987 | G13: =IFERROR(G90/F90-1,"") -> 0.20737327 | H13: =IFERROR(H90/G90-1,"") -> 0.08778626 | I13: =IFERROR(I90/H90-1,"") -> -0.035087719 | J13: =IFERROR(J90/I90-1,"") -> 0.10545455 | K13: =IFERROR(K90/J90-1,"") -> 0.20723684 | ... M13: =IFERROR(M90/L90-1,"") -> 0.016129032
A14: International destinations growth (capacity proxy) | B14: % | D14: =IFERROR(D91/C91-1,"") -> 0.2 | E14: =IFERROR(E91/D91-1,"") -> 0.33333333 | F14: =IFERROR(F91/E91-1,"") -> 1 | G14: =IFERROR(G91/F91-1,"") -> 0.5 | H14: =IFERROR(H91/G91-1,"") -> -0.58333333 | I14: =IFERROR(I91/H91-1,"") -> 0.5 | J14: =IFERROR(J91/I91-1,"") -> 0.46666667 | K14: =IFERROR(K91/J91-1,"") -> 0.36363636 | ... M14: =IFERROR(M91/L91-1,"") -> 0.125
A15: Peak daily flights growth | B15: % | D15: =IFERROR(D92/C92-1,"") -> 0.22571819 | E15: =IFERROR(E92/D92-1,"") -> 0.21205357 | F15: =IFERROR(F92/E92-1,"") -> 0.26703499 | G15: =IFERROR(G92/F92-1,"") -> 0.21656977 | H15: =IFERROR(H92/G92-1,"") -> -0.22281959 | I15: =IFERROR(I92/H92-1,"") -> 0.2121445 | J15: =IFERROR(J92/I92-1,"") -> 0.15091947 | K15: =IFERROR(K92/J92-1,"") -> 0.11349862 | ... M15: =IFERROR(M92/L92-1,"") -> -0.02734375
A17: Unit Economics
A18: Load factor | B18: % | C18: =C93 -> 0.83983189 | D18: =D93 -> 0.84811286 | E18: =E93 -> 0.87401575 | F18: =F93 -> 0.8617284 | G18: =G93 -> 0.85758836 | H18: =H93 -> 0.6938326 | I18: =I93 -> 0.73579545 | J18: =J93 -> 0.8208042 | ... M18: =M93 -> 0.84396752
A19: Yield | B19: INR / passenger km | C19: =C94 -> 3.91 | D19: =D94 -> 3.5 | E19: =E94 -> 3.59 | F19: =F94 -> 3.6 | G19: =G94 -> 3.81 | H19: =H94 -> 3.76 | I19: =I94 -> 4.24 | J19: =J94 -> 5.13 | ... M19: =M94 -> 5.06
A20: Reported RASK | B20: INR / ASK | C20: =C95 -> 3.78 | D20: =D95 -> 3.44 | E20: =E95 -> 3.64 | F20: =F95 -> 3.57 | G20: =G95 -> 3.77 | H20: =H95 -> 3.3 | I20: =I95 -> 3.73 | J20: =J95 -> 4.8 | ... M20: =M95 -> 4.99
A21: Reported CASK | B21: INR / ASK | C21: =C96 -> 3.12 | D21: =D96 -> 3.04 | E21: =E96 -> 3.15 | F21: =F96 -> 3.59 | G21: =G96 -> 3.8 | H21: =H96 -> 4.58 | I21: =I96 -> 4.6 | J21: =J96 -> 4.83 | ... M21: =M96 -> 5
A22: Reported ex-fuel CASK | B22: INR / ASK | C22: =C97 -> 2.01 | D22: =D97 -> 1.88 | E22: =E97 -> 1.93 | F22: =F97 -> 2.11 | G22: =G97 -> 2.5 | H22: =H97 -> 3.74 | I22: =I97 -> 3.22 | J22: =J97 -> 2.76 | ... M22: =M97 -> 3.52
A23: Revenue / ASK | B23: INR / ASK | C23: =IFERROR(C58/C87/100,"") -> 3.7683654 | D23: =IFERROR(D58/D87/100,"") -> 3.404269 | E23: =IFERROR(E58/E87/100,"") -> 3.6253365 | F23: =IFERROR(F58/F87/100,"") -> 3.51812 | G23: =IFERROR(G58/G87/100,"") -> 3.71684 | H23: =IFERROR(H58/H87/100,"") -> 3.2248086 | I23: =IFERROR(I58/I87/100,"") -> 3.6833703 | J23: =IFERROR(J58/J87/100,"") -> 4.7593053 | ... M23: =IFERROR(M58/M87/100,"") -> 4.9281845
A24: Fuel cost / ASK | B24: INR / ASK | C24: =IFERROR(C59/C87/100,"") -> 1.1158823 | D24: =IFERROR(D59/D87/100,"") -> 1.1618749 | E24: =IFERROR(E59/E87/100,"") -> 1.2220687 | F24: =IFERROR(F59/F87/100,"") -> 1.4744189 | G24: =IFERROR(G59/G87/100,"") -> 1.2945732 | H24: =IFERROR(H59/H87/100,"") -> 0.84389361 | I24: =IFERROR(I59/I87/100,"") -> 1.3771642 | J24: =IFERROR(J59/J87/100,"") -> 2.0669595 | ... M24: =IFERROR(M59/M87/100,"") -> 1.4726914
A25: Employee cost / ASK | B25: INR / ASK | C25: =IFERROR(C60/C87/100,"") -> 0.41791338 | D25: =IFERROR(D60/D87/100,"") -> 0.37526383 | E25: =IFERROR(E60/E87/100,"") -> 0.38661764 | F25: =IFERROR(F60/F87/100,"") -> 0.39636506 | G25: =IFERROR(G60/G87/100,"") -> 0.48960073 | H25: =IFERROR(H60/H87/100,"") -> 0.7258793 | I25: =IFERROR(I60/I87/100,"") -> 0.49523338 | J25: =IFERROR(J60/J87/100,"") -> 0.41912168 | ... M25: =IFERROR(M60/M87/100,"") -> 0.47982599
A26: Supplementary rentals and maintenance / ASK | B26: INR / ASK | C26: =IF(C61=0,"",C61/C87/100) | D26: =IF(D61=0,"",D61/D87/100) | E26: =IF(E61=0,"",E61/E87/100) | F26: =IF(F61=0,"",F61/F87/100) | G26: =IF(G61=0,"",G61/G87/100) -> 0.6098999 | H26: =IF(H61=0,"",H61/H87/100) -> 0.92318502 | I26: =IF(I61=0,"",I61/I87/100) -> 0.86502614 | J26: =IF(J61=0,"",J61/J87/100) -> 0.70323077 | ... M26: =IF(M61=0,"",M61/M87/100) -> 0.74896172
A27: EBITDAR proxy / ASK | B27: INR / ASK | C27: =IFERROR(C70/C87/100,"") -> 1.3332461 | D27: =IFERROR(D70/D87/100,"") -> 1.0381785 | E27: =IFERROR(E70/E87/100,"") -> 1.1201123 | F27: =IFERROR(F70/F87/100,"") -> 0.70200037 | G27: =IFERROR(G70/G87/100,"") -> 0.6064052 | H27: =IFERROR(H70/H87/100,"") -> 0.25922643 | I27: =IFERROR(I70/I87/100,"") -> 0.21549574 | J27: =IFERROR(J70/J87/100,"") -> 0.6981118 | ... M27: =IFERROR(M70/M87/100,"") -> 0.9000348
A28: EBITDA / ASK | B28: INR / ASK | C28: =IFERROR(C69/C87/100,"") -> 0.72335769 | D28: =IFERROR(D69/D87/100,"") -> 0.46555606 | E28: =IFERROR(E69/E87/100,"") -> 0.55157701 | F28: =IFERROR(F69/F87/100,"") -> 0.084784444 | G28: =IFERROR(G69/G87/100,"") -> 0.55477765 | H28: =IFERROR(H69/H87/100,"") -> 0.19745176 | I28: =IFERROR(I69/I87/100,"") -> 0.17122244 | J28: =IFERROR(J69/J87/100,"") -> 0.66962928 | ... M28: =IFERROR(M69/M87/100,"") -> 0.77911253
A29: EBIT / ASK | B29: INR / ASK | C29: =IFERROR(C68/C87/100,"") -> 0.6058982 | D29: =IFERROR(D68/D87/100,"") -> 0.38177941 | E29: =IFERROR(E68/E87/100,"") -> 0.48277748 | F29: =IFERROR(F68/F87/100,"") -> -0.0089908642 | G29: =IFERROR(G68/G87/100,"") -> 0.14168732 | H29: =IFERROR(H68/H87/100,"") -> -0.8376685 | I29: =IFERROR(I68/I87/100,"") -> -0.54874915 | J29: =IFERROR(J68/J87/100,"") -> 0.22356556 | ... M29: =IFERROR(M68/M87/100,"") -> 0.15218677
A30: Revenue / passenger | B30: INR / passenger | C30: =IFERROR(C58*10/C89,"") -> 4875.5163 | D30: =IFERROR(D58*10/D89,"") -> 4268.2395 | E30: =IFERROR(E58*10/E89,"") -> 4415.0372 | F30: =IFERROR(F58*10/F89,"") -> 4401.5217 | G30: =IFERROR(G58*10/G89,"") -> 4765.8147 | H30: =IFERROR(H58*10/H89,"") -> 4768.9352 | I30: =IFERROR(I58*10/I89,"") -> 5207.0135 | J30: =IFERROR(J58*10/J89,"") -> 6360.5669 | ... M30: =IFERROR(M58*10/M89,"") -> 6885.081
A31: PAT / passenger | B31: INR / passenger | C31: =IFERROR(C71*10/C89,"") -> 601.05123 | D31: =IFERROR(D71*10/D89,"") -> 381.13273 | E31: =IFERROR(E71*10/E89,"") -> 430.04181 | F31: =IFERROR(F71*10/F89,"") -> 24.287877 | G31: =IFERROR(G71*10/G89,"") -> -31.146269 | H31: =IFERROR(H71*10/H89,"") -> -1891.3443 | I31: =IFERROR(I71*10/I89,"") -> -1237.3183 | J31: =IFERROR(J71*10/J89,"") -> -35.723014 | ... M31: =IFERROR(M71*10/M89,"") -> -193.97083
A32: Margins and Returns
A33: EBITDAR proxy margin | B33: % | C33: =IFERROR(C70/C58,"") -> 0.35379958 | D33: =IFERROR(D70/D58,"") -> 0.3049637 | E33: =IFERROR(E70/E58,"") -> 0.30896781 | F33: =IFERROR(F70/F58,"") -> 0.1995385 | G33: =IFERROR(G70/G58,"") -> 0.16315074 | H33: =IFERROR(H70/H58,"") -> 0.08038506 | I33: =IFERROR(I70/I58,"") -> 0.058505043 | J33: =IFERROR(J70/J58,"") -> 0.14668355 | ... M33: =IFERROR(M70/M58,"") -> 0.1826301
A34: EBITDA margin | B34: % | C34: =IFERROR(C69/C58,"") -> 0.1919553 | D34: =IFERROR(D69/D58,"") -> 0.13675655 | E34: =IFERROR(E69/E58,"") -> 0.15214505 | F34: =IFERROR(F69/F58,"") -> 0.024099361 | G34: =IFERROR(G69/G58,"") -> 0.14926057 | H34: =IFERROR(H69/H58,"") -> 0.061228987 | I34: =IFERROR(I69/I58,"") -> 0.046485264 | J34: =IFERROR(J69/J58,"") -> 0.14069895 | ... M34: =IFERROR(M69/M58,"") -> 0.15809322
A35: EBIT margin | B35: % | C35: =IFERROR(C68/C58,"") -> 0.16078542 | D35: =IFERROR(D68/D58,"") -> 0.11214725 | E35: =IFERROR(E68/E58,"") -> 0.13316763 | F35: =IFERROR(F68/F58,"") -> -0.0025555877 | G35: =IFERROR(G68/G58,"") -> 0.03812037 | H35: =IFERROR(H68/H58,"") -> -0.25975759 | I35: =IFERROR(I68/I58,"") -> -0.14898017 | J35: =IFERROR(J68/J58,"") -> 0.04697441 | ... M35: =IFERROR(M68/M58,"") -> 0.030880901
A36: PAT margin | B36: % | C36: =IFERROR(C71/C58,"") -> 0.12327951 | D36: =IFERROR(D71/D58,"") -> 0.089295067 | E36: =IFERROR(E71/E58,"") -> 0.097403892 | F36: =IFERROR(F71/F58,"") -> 0.0055180636 | G36: =IFERROR(G71/G58,"") -> -0.0065353505 | H36: =IFERROR(H71/H58,"") -> -0.39659677 | I36: =IFERROR(I71/I58,"") -> -0.23762533 | J36: =IFERROR(J71/J58,"") -> -0.0056163255 | ... M36: =IFERROR(M71/M58,"") -> -0.028172628
A37: ROE | B37: % | D37: =IF(AVERAGE(C75,D75)>0,D71/AVERAGE(C75,D75),"") -> 0.59113241 | E37: =IF(AVERAGE(D75,E75)>0,E71/AVERAGE(D75,E75),"") -> 0.41308296 | F37: =IF(AVERAGE(E75,F75)>0,F71/AVERAGE(E75,F75),"") -> 0.022426749 | G37: =IF(AVERAGE(F75,G75)>0,G71/AVERAGE(F75,G75),"") -> -0.036444566 | H37: =IF(AVERAGE(G75,H75)>0,H71/AVERAGE(G75,H75),"") -> -1.9390956 | I37: =IF(AVERAGE(H75,I75)>0,I71/AVERAGE(H75,I75),"") | J37: =IF(AVERAGE(I75,J75)>0,J71/AVERAGE(I75,J75),"") | K37: =IF(AVERAGE(J75,K75)>0,K71/AVERAGE(J75,K75),"") | ... M37: =IF(AVERAGE(L75,M75)>0,M71/AVERAGE(L75,M75),"") -> -0.29269486
A39: Asset turnover | B39: x | D39: =IFERROR(D58/AVERAGE(C74,D74),"") -> 1.3164193 | E39: =IFERROR(E58/AVERAGE(D74,E74),"") -> 1.2670061 | F39: =IFERROR(F58/AVERAGE(E74,F74),"") -> 1.2347988 | G39: =IFERROR(G58/AVERAGE(F74,G74),"") -> 1.0653094 | H39: =IFERROR(H58/AVERAGE(G74,H74),"") -> 0.34386958 | I39: =IFERROR(I58/AVERAGE(H74,I74),"") -> 0.58262744 | J39: =IFERROR(J58/AVERAGE(I74,J74),"") -> 1.0357691 | K39: =IFERROR(K58/AVERAGE(J74,K74),"") -> 0.97464077 | ... M39: =IFERROR(M58/AVERAGE(L74,M74),"") -> 0.67471419
A40: Effective tax rate | B40: % | C40: =IF(C66>0,C67/C66,"") -> 0.29665777 | D40: =IF(D66>0,D67/D66,"") -> 0.22625203 | E40: =IF(E66>0,E67/E66,"") -> 0.28282971 | F40: =IF(F66>0,F67/F66,"") | G40: =IF(G66>0,G67/G66,"") | H40: =IF(H66>0,H67/H66,"") | I40: =IF(I66>0,I67/I66,"") | J40: =IF(J66>0,J67/J66,"") | ... M40: =IF(M66>0,M67/M66,"")
A42: Cash Conversion
A44: CFO / EBITDA | B44: x | C44: =IFERROR(C72/C69,"") -> 1.0003015 | D44: =IFERROR(D72/D69,"") -> 1.488415 | E44: =IFERROR(E72/E69,"") -> 1.1143664 | F44: =IFERROR(F72/F69,"") -> 4.6239862 | G44: =IFERROR(G72/G69,"") -> 1.3063206 | H44: =IFERROR(H72/H69,"") -> -1.800645 | I44: =IFERROR(I72/I69,"") -> 1.7343352 | J44: =IFERROR(J72/J69,"") -> 1.6614896 | ... M44: =IFERROR(M72/M69,"") -> 1.7473254
A45: FCF / revenue | B45: % | C45: =IFERROR(C73/C58,"") -> 0.17763948 | D45: =IFERROR(D73/D58,"") -> 0.19078238 | E45: =IFERROR(E73/E58,"") -> 0.11654064 | F45: =IFERROR(F73/F58,"") -> 0.051373503 | G45: =IFERROR(G73/G58,"") -> 0.16454513 | H45: =IFERROR(H73/H58,"") -> -0.14009239 | I45: =IFERROR(I73/I58,"") -> 0.067243913 | J45: =IFERROR(J73/J58,"") -> 0.22330445 | ... M45: =IFERROR(M73/M58,"") -> 0.24950125
A48: Balance Sheet and Leverage
A49: Gross borrowings | B49: INR crore | C49: =C80 -> 2949.861 | D49: =D80 -> 2395.708 | E49: =E80 -> 2241.37 | F49: =F80 -> 2193.669 | G49: =G80 -> 346.587 | H49: =H80 -> 2505.623 | I49: =I80 -> 3896.736 | J49: =J80 -> 2252.337 | ... M49: =M80 -> 1806.3
A50: Lease liabilities | B50: INR crore | C50: =C81 -> 0 | D50: =D81 -> 0 | E50: =E81 -> 0 | F50: =F81 -> 0 | G50: =G81 -> 22033.528 | H50: =H81 -> 27354.031 | I50: =I81 -> 32981.101 | J50: =J81 -> 42601.876 | ... M50: =M81 -> 75942.9
A51: Cash and liquid balances | B51: INR crore | C51: =C82 -> 4692.815 | D51: =D82 -> 8345.973 | E51: =E82 -> 12924.62 | F51: =F82 -> 15138.582 | G51: =G82 -> 20371.672 | H51: =H82 -> 18567.154 | I51: =I82 -> 18226.625 | J51: =J82 -> 23397.782 | ... M51: =M82 -> 51674.1
A52: Net financial debt / (cash) | B52: INR crore | C52: =C83 -> -1742.954 | D52: =D83 -> -5950.265 | E52: =E83 -> -10683.25 | F52: =F83 -> -12944.913 | G52: =G83 -> -20025.085 | H52: =H83 -> -16061.531 | I52: =I83 -> -14329.889 | J52: =J83 -> -21145.445 | ... M52: =M83 -> -49867.8
A53: Lease-adjusted net debt | B53: INR crore | C53: =C84 -> -1742.954 | D53: =D84 -> -5950.265 | E53: =E84 -> -10683.25 | F53: =F84 -> -12944.913 | G53: =G84 -> 2008.443 | H53: =H84 -> 11292.5 | I53: =I84 -> 18651.212 | J53: =J84 -> 21456.431 | ... M53: =M84 -> 26075.1
A54: Lease-adjusted leverage | B54: x | C54: =IF(C70>0,C84/C70,"") -> -0.30523022 | D54: =IF(D70>0,D84/D70,"") -> -1.0501003 | E54: =IF(E70>0,E84/E70,"") -> -1.5019937 | F54: =IF(F70>0,F84/F70,"") -> -2.2765478 | G54: =IF(G70>0,G84/G70,"") -> 0.34428771 | H54: =IF(H70>0,H84/H70,"") -> 9.5952206 | I54: =IF(I70>0,I84/I70,"") -> 12.294071 | J54: =IF(J70>0,J84/J70,"") -> 2.6866215 | ... M54: =IF(M70>0,M84/M70,"") -> 1.6804648
A55: Interest coverage | B55: x | C55: =IF(C64<>0,C68/C64,"") -> 19.243636 | D55: =IF(D64<>0,D68/D64,"") -> 6.2995102 | E55: =IF(E64<>0,E68/E64,"") -> 9.0214882 | F55: =IF(F64<>0,F68/F64,"") -> -0.14308702 | G55: =IF(G64<>0,G68/G64,"") -> 0.72661286 | H55: =IF(H64<>0,H68/H64,"") -> -1.7754646 | I55: =IF(I64<>0,I68/I64,"") -> -1.6383246 | J55: =IF(J64<>0,J68/J64,"") -> 0.81666976 | ... M55: =IF(M64<>0,M68/M64,"") -> 0.44538942
A56: Lease liabilities / EBITDAR proxy | B56: x | C56: =IF(C70>0,C81/C70,"") -> 0 | D56: =IF(D70>0,D81/D70,"") -> 0 | E56: =IF(E70>0,E81/E70,"") -> 0 | F56: =IF(F70>0,F81/F70,"") -> 0 | G56: =IF(G70>0,G81/G70,"") -> 3.7769919 | H56: =IF(H70>0,H81/H70,"") -> 23.24268 | I56: =IF(I70>0,I81/I70,"") -> 21.739713 | J56: =IF(J70>0,J81/J70,"") -> 5.3343035 | ... M56: =IF(M70>0,M81/M70,"") -> 4.8943003
A57: Supporting Calculations
A58: Revenue from operations | B58: INR crore | C58: ='02_Raw_Financials'!C8 -> 16139.909 | D58: ='02_Raw_Financials'!D8 -> 18580.5 | E58: ='02_Raw_Financials'!E8 -> 23020.887 | F58: ='02_Raw_Financials'!F8 -> 28496.772 | G58: ='02_Raw_Financials'!G8 -> 35756.001 | H58: ='02_Raw_Financials'!H8 -> 14640.631 | I58: ='02_Raw_Financials'!I8 -> 25930.927 | J58: ='02_Raw_Financials'!J8 -> 54446.453 | ... M58: ='02_Raw_Financials'!M8 -> 84961.9
A59: Aircraft fuel expense | B59: INR crore | C59: ='02_Raw_Financials'!C11 -> 4779.324 | D59: ='02_Raw_Financials'!D11 -> 6341.513 | E59: ='02_Raw_Financials'!E11 -> 7760.136 | F59: ='02_Raw_Financials'!F11 -> 11942.793 | G59: ='02_Raw_Financials'!G11 -> 12453.794 | H59: ='02_Raw_Financials'!H11 -> 3831.277 | I59: ='02_Raw_Financials'!I11 -> 9695.236 | J59: ='02_Raw_Financials'!J11 -> 23646.017 | ... M59: ='02_Raw_Financials'!M11 -> 25389.2
A60: Employee expense | B60: INR crore | C60: ='02_Raw_Financials'!C17 -> 1789.923 | D60: ='02_Raw_Financials'!D17 -> 2048.19 | E60: ='02_Raw_Financials'!E17 -> 2455.022 | F60: ='02_Raw_Financials'!F17 -> 3210.557 | G60: ='02_Raw_Financials'!G17 -> 4709.959 | H60: ='02_Raw_Financials'!H17 -> 3295.492 | I60: ='02_Raw_Financials'!I17 -> 3486.443 | J60: ='02_Raw_Financials'!J17 -> 4794.752 | ... M60: ='02_Raw_Financials'!M17 -> 8272.2
A61: Supplementary rentals and maintenance | B61: INR crore | C61: ='02_Raw_Financials'!C13 -> 0 | D61: ='02_Raw_Financials'!D13 -> 0 | E61: ='02_Raw_Financials'!E13 -> 0 | F61: ='02_Raw_Financials'!F13 -> 0 | G61: ='02_Raw_Financials'!G13 -> 5867.237 | H61: ='02_Raw_Financials'!H13 -> 4191.26 | I61: ='02_Raw_Financials'!I13 -> 6089.784 | J61: ='02_Raw_Financials'!J13 -> 8044.96 | ... M61: ='02_Raw_Financials'!M13 -> 12912.1
A62: Aircraft and engine rentals | B62: INR crore | C62: ='02_Raw_Financials'!C12 -> 2612.152 | D62: ='02_Raw_Financials'!D12 -> 3125.373 | E62: ='02_Raw_Financials'!E12 -> 3610.199 | F62: ='02_Raw_Financials'!F12 -> 4999.449 | G62: ='02_Raw_Financials'!G12 -> 496.657 | H62: ='02_Raw_Financials'!H12 -> 280.457 | I62: ='02_Raw_Financials'!I12 -> 311.684 | J62: ='02_Raw_Financials'!J12 -> 325.84 | ... M62: ='02_Raw_Financials'!M12 -> 2084.7
A63: Depreciation and amortisation | B63: INR crore | C63: ='02_Raw_Financials'!C20 -> 503.079 | D63: ='02_Raw_Financials'!D20 -> 457.253 | E63: ='02_Raw_Financials'!E20 -> 436.877 | F63: ='02_Raw_Financials'!F20 -> 759.58 | G63: ='02_Raw_Financials'!G20 -> 3973.929 | H63: ='02_Raw_Financials'!H20 -> 4699.446 | I63: ='02_Raw_Financials'!I20 -> 5068.6 | J63: ='02_Raw_Financials'!J20 -> 5102.969 | ... M63: ='02_Raw_Financials'!M20 -> 10808.2
A64: Finance costs | B64: INR crore | C64: ='02_Raw_Financials'!C21 -> 134.853 | D64: ='02_Raw_Financials'!D21 -> 330.78 | E64: ='02_Raw_Financials'!E21 -> 339.815 | F64: ='02_Raw_Financials'!F21 -> 508.963 | G64: ='02_Raw_Financials'!G21 -> 1875.871 | H64: ='02_Raw_Financials'!H21 -> 2141.983 | I64: ='02_Raw_Financials'!I21 -> 2358.015 | J64: ='02_Raw_Financials'!J21 -> 3131.731 | ... M64: ='02_Raw_Financials'!M21 -> 5890.8
A65: Interest income | B65: INR crore | C65: ='02_Raw_Financials'!C85 -> -368.741 | D65: ='02_Raw_Financials'!D85 -> -391.327 | E65: ='02_Raw_Financials'!E85 -> -400.805 | F65: ='02_Raw_Financials'!F85 -> -434.411 | G65: ='02_Raw_Financials'!G85 -> -257.17 | H65: ='02_Raw_Financials'!H85 -> -126.928 | I65: ='02_Raw_Financials'!I85 -> -67.525 | J65: ='02_Raw_Financials'!J85 -> -269.756 | ... M65: ='02_Raw_Financials'!M85 -> -1306.6
A66: Profit before tax | B66: INR crore | C66: ='02_Raw_Financials'!C24 -> 2828.95 | D66: ='02_Raw_Financials'!D24 -> 2144.299 | E66: ='02_Raw_Financials'!E24 -> 3126.627 | F66: ='02_Raw_Financials'!F24 -> -147.378 | G66: ='02_Raw_Financials'!G24 -> -255.669 | H66: ='02_Raw_Financials'!H24 -> -5818.07 | I66: ='02_Raw_Financials'!I24 -> -6153.684 | J66: ='02_Raw_Financials'!J24 -> -304.385 | ... M66: ='02_Raw_Financials'!M24 -> -1960.5
A67: Tax expense / (credit) | B67: INR crore | C67: ='02_Raw_Financials'!C25 -> 839.23 | D67: ='02_Raw_Financials'!D25 -> 485.152 | E67: ='02_Raw_Financials'!E25 -> 884.303 | F67: ='02_Raw_Financials'!F25 -> -304.625 | G67: ='02_Raw_Financials'!G25 -> -21.991 | H67: ='02_Raw_Financials'!H25 -> -11.643 | I67: ='02_Raw_Financials'!I25 -> 8.161 | J67: ='02_Raw_Financials'!J25 -> 1.404 | ... M67: ='02_Raw_Financials'!M25 -> 433.1
A68: EBIT (reported) | B68: INR crore | C68: =C66+C64+C65 -> 2595.062 | D68: =D66+D64+D65 -> 2083.752 | E68: =E66+E64+E65 -> 3065.637 | F68: =F66+F64+F65 -> -72.826 | G68: =G66+G64+G65 -> 1363.032 | H68: =H66+H64+H65 -> -3803.015 | I68: =I66+I64+I65 -> -3863.194 | J68: =J66+J64+J65 -> 2557.59 | ... M68: =M66+M64+M65 -> 2623.7
A69: EBITDA | B69: INR crore | C69: =C68+C63 -> 3098.141 | D69: =D68+D63 -> 2541.005 | E69: =E68+E63 -> 3502.514 | F69: =F68+F63 -> 686.754 | G69: =G68+G63 -> 5336.961 | H69: =H68+H63 -> 896.431 | I69: =I68+I63 -> 1205.406 | J69: =J68+J63 -> 7660.559 | ... M69: =M68+M63 -> 13431.9
A70: EBITDAR proxy | B70: INR crore | C70: =C69+C62 -> 5710.293 | D70: =D69+D62 -> 5666.378 | E70: =E69+E62 -> 7112.713 | F70: =F69+F62 -> 5686.203 | G70: =G69+G62 -> 5833.618 | H70: =H69+H62 -> 1176.888 | I70: =I69+I62 -> 1517.09 | J70: =J69+J62 -> 7986.399 | ... M70: =M69+M62 -> 15516.6
A71: Profit after tax | B71: INR crore | C71: ='02_Raw_Financials'!C26 -> 1989.72 | D71: ='02_Raw_Financials'!D26 -> 1659.147 | E71: ='02_Raw_Financials'!E26 -> 2242.324 | F71: ='02_Raw_Financials'!F26 -> 157.247 | G71: ='02_Raw_Financials'!G26 -> -233.678 | H71: ='02_Raw_Financials'!H26 -> -5806.427 | I71: ='02_Raw_Financials'!I26 -> -6161.845 | J71: ='02_Raw_Financials'!J26 -> -305.789 | ... M71: ='02_Raw_Financials'!M26 -> -2393.6
A72: Cash flow from operations | B72: INR crore | C72: ='02_Raw_Financials'!C91 -> 3099.075 | D72: ='02_Raw_Financials'!D91 -> 3782.07 | E72: ='02_Raw_Financials'!E91 -> 3903.084 | F72: ='02_Raw_Financials'!F91 -> 3175.541 | G72: ='02_Raw_Financials'!G91 -> 6971.782 | H72: ='02_Raw_Financials'!H91 -> -1614.154 | I72: ='02_Raw_Financials'!I91 -> 2090.578 | J72: ='02_Raw_Financials'!J91 -> 12727.939 | ... M72: ='02_Raw_Financials'!M91 -> 23469.9
A73: Basic free cash flow | B73: INR crore | C73: ='02_Raw_Financials'!C93 -> 2867.085 | D73: ='02_Raw_Financials'!D93 -> 3544.832 | E73: ='02_Raw_Financials'!E93 -> 2682.869 | F73: ='02_Raw_Financials'!F93 -> 1463.979 | G73: ='02_Raw_Financials'!G93 -> 5883.476 | H73: ='02_Raw_Financials'!H93 -> -2051.041 | I73: ='02_Raw_Financials'!I93 -> 1743.697 | J73: ='02_Raw_Financials'!J93 -> 12158.135 | ... M73: ='02_Raw_Financials'!M93 -> 21198.1
A74: Total assets | B74: INR crore | C74: ='02_Raw_Financials'!C55 -> 13019.111 | D74: ='02_Raw_Financials'!D55 -> 15209.736 | E74: ='02_Raw_Financials'!E55 -> 21129.296 | F74: ='02_Raw_Financials'!F55 -> 25026.842 | G74: ='02_Raw_Financials'!G55 -> 42101.078 | H74: ='02_Raw_Financials'!H55 -> 43051.153 | I74: ='02_Raw_Financials'!I55 -> 45962.598 | J74: ='02_Raw_Financials'!J55 -> 59169.819 | ... M74: ='02_Raw_Financials'!M55 -> 136002.1
A75: Total equity | B75: INR crore | C75: ='02_Raw_Financials'!C58 -> 1834.277 | D75: ='02_Raw_Financials'!D58 -> 3779.176 | E75: ='02_Raw_Financials'!E58 -> 7077.355 | F75: ='02_Raw_Financials'!F58 -> 6945.81 | G75: ='02_Raw_Financials'!G58 -> 5877.94 | H75: ='02_Raw_Financials'!H58 -> 110.859 | I75: ='02_Raw_Financials'!I58 -> -5988.062 | J75: ='02_Raw_Financials'!J58 -> -6246.516 | ... M75: ='02_Raw_Financials'!M58 -> 6987.4
A76: Cash and cash equivalents | B76: INR crore | C76: ='02_Raw_Financials'!C48 -> 805.368 | D76: ='02_Raw_Financials'!D48 -> 153.119 | E76: ='02_Raw_Financials'!E48 -> 670.718 | F76: ='02_Raw_Financials'!F48 -> 728.417 | G76: ='02_Raw_Financials'!G48 -> 719.066 | H76: ='02_Raw_Financials'!H48 -> 508.885 | I76: ='02_Raw_Financials'!I48 -> 1015.329 | J76: ='02_Raw_Financials'!J48 -> 1267.969 | ... M76: ='02_Raw_Financials'!M48 -> 1323.9
A77: Other bank balances | B77: INR crore | C77: ='02_Raw_Financials'!C49 -> 2913.302 | D77: ='02_Raw_Financials'!D49 -> 4479.426 | E77: ='02_Raw_Financials'!E49 -> 5909.973 | F77: ='02_Raw_Financials'!F49 -> 7893.58 | G77: ='02_Raw_Financials'!G49 -> 10153.364 | H77: ='02_Raw_Financials'!H49 -> 10718.78 | I77: ='02_Raw_Financials'!I49 -> 9104.812 | J77: ='02_Raw_Financials'!J49 -> 10571.716 | ... M77: ='02_Raw_Financials'!M49 -> 22675.4
A78: Current investments | B78: INR crore | C78: ='02_Raw_Financials'!C46 -> 974.12 | D78: ='02_Raw_Financials'!D46 -> 3713.41 | E78: ='02_Raw_Financials'!E46 -> 6343.912 | F78: ='02_Raw_Financials'!F46 -> 6516.57 | G78: ='02_Raw_Financials'!G46 -> 9499.167 | H78: ='02_Raw_Financials'!H46 -> 7339.406 | I78: ='02_Raw_Financials'!I46 -> 8106.472 | J78: ='02_Raw_Financials'!J46 -> 11558.029 | ... M78: ='02_Raw_Financials'!M46 -> 25743.8
A79: Non-current investments | B79: INR crore | C79: ='02_Raw_Financials'!C38 -> 0.025 | D79: ='02_Raw_Financials'!D38 -> 0.018 | E79: ='02_Raw_Financials'!E38 -> 0.017 | F79: ='02_Raw_Financials'!F38 -> 0.015 | G79: ='02_Raw_Financials'!G38 -> 0.075 | H79: ='02_Raw_Financials'!H38 -> 0.083 | I79: ='02_Raw_Financials'!I38 -> 0.012 | J79: ='02_Raw_Financials'!J38 -> 0.068 | ... M79: ='02_Raw_Financials'!M38 -> 1931
A80: Gross borrowings | B80: INR crore | C80: ='02_Raw_Financials'!C59+'02_Raw_Financials'!C67 -> 2949.861 | D80: ='02_Raw_Financials'!D59+'02_Raw_Financials'!D67 -> 2395.708 | E80: ='02_Raw_Financials'!E59+'02_Raw_Financials'!E67 -> 2241.37 | F80: ='02_Raw_Financials'!F59+'02_Raw_Financials'!F67 -> 2193.669 | G80: ='02_Raw_Financials'!G59+'02_Raw_Financials'!G67 -> 346.587 | H80: ='02_Raw_Financials'!H59+'02_Raw_Financials'!H67 -> 2505.623 | I80: ='02_Raw_Financials'!I59+'02_Raw_Financials'!I67 -> 3896.736 | J80: ='02_Raw_Financials'!J59+'02_Raw_Financials'!J67 -> 2252.337 | ... M80: ='02_Raw_Financials'!M59+'02_Raw_Financials'!M67 -> 1806.3
A81: Lease liabilities | B81: INR crore | C81: ='02_Raw_Financials'!C60+'02_Raw_Financials'!C68 -> 0 | D81: ='02_Raw_Financials'!D60+'02_Raw_Financials'!D68 -> 0 | E81: ='02_Raw_Financials'!E60+'02_Raw_Financials'!E68 -> 0 | F81: ='02_Raw_Financials'!F60+'02_Raw_Financials'!F68 -> 0 | G81: ='02_Raw_Financials'!G60+'02_Raw_Financials'!G68 -> 22033.528 | H81: ='02_Raw_Financials'!H60+'02_Raw_Financials'!H68 -> 27354.031 | I81: ='02_Raw_Financials'!I60+'02_Raw_Financials'!I68 -> 32981.101 | J81: ='02_Raw_Financials'!J60+'02_Raw_Financials'!J68 -> 42601.876 | ... M81: ='02_Raw_Financials'!M60+'02_Raw_Financials'!M68 -> 75942.9
A82: Gross liquidity pool | B82: INR crore | C82: =C76+C77+C78+C79 -> 4692.815 | D82: =D76+D77+D78+D79 -> 8345.973 | E82: =E76+E77+E78+E79 -> 12924.62 | F82: =F76+F77+F78+F79 -> 15138.582 | G82: =G76+G77+G78+G79 -> 20371.672 | H82: =H76+H77+H78+H79 -> 18567.154 | I82: =I76+I77+I78+I79 -> 18226.625 | J82: =J76+J77+J78+J79 -> 23397.782 | ... M82: =M76+M77+M78+M79 -> 51674.1
A83: Net borrowings / (gross liquidity) | B83: INR crore | C83: =C80-C82 -> -1742.954 | D83: =D80-D82 -> -5950.265 | E83: =E80-E82 -> -10683.25 | F83: =F80-F82 -> -12944.913 | G83: =G80-G82 -> -20025.085 | H83: =H80-H82 -> -16061.531 | I83: =I80-I82 -> -14329.889 | J83: =J80-J82 -> -21145.445 | ... M83: =M80-M82 -> -49867.8
A84: Lease-adjusted net debt | B84: INR crore | C84: =C83+C81 -> -1742.954 | D84: =D83+D81 -> -5950.265 | E84: =E83+E81 -> -10683.25 | F84: =F83+F81 -> -12944.913 | G84: =G83+G81 -> 2008.443 | H84: =H83+H81 -> 11292.5 | I84: =I83+I81 -> 18651.212 | J84: =J83+J81 -> 21456.431 | ... M84: =M83+M81 -> 26075.1
A87: ASK | B87: billion | C87: ='03_Raw_Operating_KPIs'!C9 -> 42.83 | D87: ='03_Raw_Operating_KPIs'!D9 -> 54.58 | E87: ='03_Raw_Operating_KPIs'!E9 -> 63.5 | F87: ='03_Raw_Operating_KPIs'!F9 -> 81 | G87: ='03_Raw_Operating_KPIs'!G9 -> 96.2 | H87: ='03_Raw_Operating_KPIs'!H9 -> 45.4 | I87: ='03_Raw_Operating_KPIs'!I9 -> 70.4 | J87: ='03_Raw_Operating_KPIs'!J9 -> 114.4 | ... M87: ='03_Raw_Operating_KPIs'!M9 -> 172.4
A88: RPK | B88: billion | C88: ='03_Raw_Operating_KPIs'!C10 -> 35.97 | D88: ='03_Raw_Operating_KPIs'!D10 -> 46.29 | E88: ='03_Raw_Operating_KPIs'!E10 -> 55.5 | F88: ='03_Raw_Operating_KPIs'!F10 -> 69.8 | G88: ='03_Raw_Operating_KPIs'!G10 -> 82.5 | H88: ='03_Raw_Operating_KPIs'!H10 -> 31.5 | I88: ='03_Raw_Operating_KPIs'!I10 -> 51.8 | J88: ='03_Raw_Operating_KPIs'!J10 -> 93.9 | ... M88: ='03_Raw_Operating_KPIs'!M10 -> 145.5
A89: Passengers | B89: million | C89: ='03_Raw_Operating_KPIs'!C12 -> 33.104 | D89: ='03_Raw_Operating_KPIs'!D12 -> 43.532 | E89: ='03_Raw_Operating_KPIs'!E12 -> 52.142 | F89: ='03_Raw_Operating_KPIs'!F12 -> 64.743 | G89: ='03_Raw_Operating_KPIs'!G12 -> 75.026 | H89: ='03_Raw_Operating_KPIs'!H12 -> 30.7 | I89: ='03_Raw_Operating_KPIs'!I12 -> 49.8 | J89: ='03_Raw_Operating_KPIs'!J12 -> 85.6 | ... M89: ='03_Raw_Operating_KPIs'!M12 -> 123.4
A90: Closing fleet | B90: aircraft | C90: ='03_Raw_Operating_KPIs'!C22 -> 107 | D90: ='03_Raw_Operating_KPIs'!D22 -> 131 | E90: ='03_Raw_Operating_KPIs'!E22 -> 159 | F90: ='03_Raw_Operating_KPIs'!F22 -> 217 | G90: ='03_Raw_Operating_KPIs'!G22 -> 262 | H90: ='03_Raw_Operating_KPIs'!H22 -> 285 | I90: ='03_Raw_Operating_KPIs'!I22 -> 275 | J90: ='03_Raw_Operating_KPIs'!J22 -> 304 | ... M90: ='03_Raw_Operating_KPIs'!M22 -> 441
A91: International destinations | B91: destinations | C91: ='03_Raw_Operating_KPIs'!C26 -> 5 | D91: ='03_Raw_Operating_KPIs'!D26 -> 6 | E91: ='03_Raw_Operating_KPIs'!E26 -> 8 | F91: ='03_Raw_Operating_KPIs'!F26 -> 16 | G91: ='03_Raw_Operating_KPIs'!G26 -> 24 | H91: ='03_Raw_Operating_KPIs'!H26 -> 10 | I91: ='03_Raw_Operating_KPIs'!I26 -> 15 | J91: ='03_Raw_Operating_KPIs'!J26 -> 22 | ... M91: ='03_Raw_Operating_KPIs'!M26 -> 45
A92: Peak daily flights | B92: flights | C92: ='03_Raw_Operating_KPIs'!C24 -> 731 | D92: ='03_Raw_Operating_KPIs'!D24 -> 896 | E92: ='03_Raw_Operating_KPIs'!E24 -> 1086 | F92: ='03_Raw_Operating_KPIs'!F24 -> 1376 | G92: ='03_Raw_Operating_KPIs'!G24 -> 1674 | H92: ='03_Raw_Operating_KPIs'!H24 -> 1301 | I92: ='03_Raw_Operating_KPIs'!I24 -> 1577 | J92: ='03_Raw_Operating_KPIs'!J24 -> 1815 | ... M92: ='03_Raw_Operating_KPIs'!M24 -> 2241
A93: Load factor | B93: % | C93: ='03_Raw_Operating_KPIs'!C11 -> 0.83983189 | D93: ='03_Raw_Operating_KPIs'!D11 -> 0.84811286 | E93: ='03_Raw_Operating_KPIs'!E11 -> 0.87401575 | F93: ='03_Raw_Operating_KPIs'!F11 -> 0.8617284 | G93: ='03_Raw_Operating_KPIs'!G11 -> 0.85758836 | H93: ='03_Raw_Operating_KPIs'!H11 -> 0.6938326 | I93: ='03_Raw_Operating_KPIs'!I11 -> 0.73579545 | J93: ='03_Raw_Operating_KPIs'!J11 -> 0.8208042 | ... M93: ='03_Raw_Operating_KPIs'!M11 -> 0.84396752
A94: Yield | B94: INR / passenger km | C94: ='03_Raw_Operating_KPIs'!C15 -> 3.91 | D94: ='03_Raw_Operating_KPIs'!D15 -> 3.5 | E94: ='03_Raw_Operating_KPIs'!E15 -> 3.59 | F94: ='03_Raw_Operating_KPIs'!F15 -> 3.6 | G94: ='03_Raw_Operating_KPIs'!G15 -> 3.81 | H94: ='03_Raw_Operating_KPIs'!H15 -> 3.76 | I94: ='03_Raw_Operating_KPIs'!I15 -> 4.24 | J94: ='03_Raw_Operating_KPIs'!J15 -> 5.13 | ... M94: ='03_Raw_Operating_KPIs'!M15 -> 5.06
A95: RASK | B95: INR / ASK | C95: ='03_Raw_Operating_KPIs'!C16 -> 3.78 | D95: ='03_Raw_Operating_KPIs'!D16 -> 3.44 | E95: ='03_Raw_Operating_KPIs'!E16 -> 3.64 | F95: ='03_Raw_Operating_KPIs'!F16 -> 3.57 | G95: ='03_Raw_Operating_KPIs'!G16 -> 3.77 | H95: ='03_Raw_Operating_KPIs'!H16 -> 3.3 | I95: ='03_Raw_Operating_KPIs'!I16 -> 3.73 | J95: ='03_Raw_Operating_KPIs'!J16 -> 4.8 | ... M95: ='03_Raw_Operating_KPIs'!M16 -> 4.99
A96: CASK | B96: INR / ASK | C96: ='03_Raw_Operating_KPIs'!C17 -> 3.12 | D96: ='03_Raw_Operating_KPIs'!D17 -> 3.04 | E96: ='03_Raw_Operating_KPIs'!E17 -> 3.15 | F96: ='03_Raw_Operating_KPIs'!F17 -> 3.59 | G96: ='03_Raw_Operating_KPIs'!G17 -> 3.8 | H96: ='03_Raw_Operating_KPIs'!H17 -> 4.58 | I96: ='03_Raw_Operating_KPIs'!I17 -> 4.6 | J96: ='03_Raw_Operating_KPIs'!J17 -> 4.83 | ... M96: ='03_Raw_Operating_KPIs'!M17 -> 5
A97: Ex-fuel CASK | B97: INR / ASK | C97: ='03_Raw_Operating_KPIs'!C18 -> 2.01 | D97: ='03_Raw_Operating_KPIs'!D18 -> 1.88 | E97: ='03_Raw_Operating_KPIs'!E18 -> 1.93 | F97: ='03_Raw_Operating_KPIs'!F18 -> 2.11 | G97: ='03_Raw_Operating_KPIs'!G18 -> 2.5 | H97: ='03_Raw_Operating_KPIs'!H18 -> 3.74 | I97: ='03_Raw_Operating_KPIs'!I18 -> 3.22 | J97: ='03_Raw_Operating_KPIs'!J18 -> 2.76 | ... M97: ='03_Raw_Operating_KPIs'!M18 -> 3.52

Sheet 06_Operating_Model
A1: Driver-Based Operating Model
A2: InterGlobe Aviation Limited | FY2024A-FY2031E
A3: Base case uses recent actual operating economics. FY2027 annual assumptions are analyst inputs, not company guidance; fuel and currency sensitivities are summarized separately.
A5: Metric | B5: Unit | C5: FY2024A | D5: FY2025A | E5: FY2026A | F5: FY2027E | G5: FY2028E | H5: FY2029E | I5: FY2030E | J5: FY2031E
A6: Period | C6: Actual | D6: Actual | E6: Actual | F6: Forecast | G6: Forecast | H6: Forecast | I6: Forecast | J6: Forecast
A8: Fleet and Capacity
A9: Beginning fleet | B9: aircraft | C9: ='03_Raw_Operating_KPIs'!J22 -> 304 | D9: ='03_Raw_Operating_KPIs'!K22 -> 367 | E9: ='03_Raw_Operating_KPIs'!L22 -> 434 | F9: =E13 -> 441 | G9: =F13 -> 473 | H9: =G13 -> 511 | I9: =H13 -> 551 | J9: =I13 -> 589
A10: Aircraft deliveries | B10: aircraft | F10: 42 | G10: 46 | H10: 48 | I10: 48 | J10: 45
A11: Aircraft retirements | B11: aircraft | F11: 10 | G11: 8 | H11: 8 | I11: 10 | J11: 10
A12: Net fleet additions | B12: aircraft | C12: ='03_Raw_Operating_KPIs'!K23 -> 63 | D12: ='03_Raw_Operating_KPIs'!L23 -> 67 | E12: ='03_Raw_Operating_KPIs'!M23 -> 7 | F12: =F10-F11 -> 32 | G12: =G10-G11 -> 38 | H12: =H10-H11 -> 40 | I12: =I10-I11 -> 38 | J12: =J10-J11 -> 35
A13: Ending fleet | B13: aircraft | C13: ='03_Raw_Operating_KPIs'!K22 -> 367 | D13: ='03_Raw_Operating_KPIs'!L22 -> 434 | E13: ='03_Raw_Operating_KPIs'!M22 -> 441 | F13: =F9+F12 -> 473 | G13: =G9+G12 -> 511 | H13: =H9+H12 -> 551 | I13: =I9+I12 -> 589 | J13: =J9+J12 -> 624
A14: Fleet growth | B14: % | C14: =C13/C9-1 -> 0.20723684 | D14: =D13/D9-1 -> 0.18256131 | E14: =E13/E9-1 -> 0.016129032 | F14: =F13/F9-1 -> 0.072562358 | G14: =G13/G9-1 -> 0.080338266 | H14: =H13/H9-1 -> 0.078277886 | I14: =I13/I9-1 -> 0.068965517 | J14: =J13/J9-1 -> 0.05942275
A15: Average fleet | B15: aircraft | C15: =AVERAGE(C9,C13) -> 335.5 | D15: =AVERAGE(D9,D13) -> 400.5 | E15: =AVERAGE(E9,E13) -> 437.5 | F15: =AVERAGE(F9,F13) -> 457 | G15: =AVERAGE(G9,G13) -> 492 | H15: =AVERAGE(H9,H13) -> 531 | I15: =AVERAGE(I9,I13) -> 570 | J15: =AVERAGE(J9,J13) -> 606.5
A16: ASK productivity / average aircraft | B16: bn ASK / aircraft | C16: ='03_Raw_Operating_KPIs'!K9/C15 -> 0.41520119 | D16: ='03_Raw_Operating_KPIs'!L9/D15 -> 0.39325843 | E16: ='03_Raw_Operating_KPIs'!M9/E15 -> 0.39405714 | F16: =E16*(1+F17) -> 0.39405714 | G16: =F16*(1+G17) -> 0.399968 | H16: =G16*(1+H17) -> 0.40596752 | I16: =H16*(1+I17) -> 0.41104211 | J16: =I16*(1+J17) -> 0.41618014
A17: ASK productivity growth | B17: % | D17: =D16/C16-1 -> -0.052848512 | E17: =E16/D16-1 -> 0.0020310204 | F17: 0 | G17: 0.015 | H17: 0.015 | I17: 0.0125 | J17: 0.0125
A18: ASK | B18: billion | C18: ='03_Raw_Operating_KPIs'!K9 -> 139.3 | D18: ='03_Raw_Operating_KPIs'!L9 -> 157.5 | E18: ='03_Raw_Operating_KPIs'!M9 -> 172.4 | F18: =F15*F16 -> 180.08411 | G18: =G15*G16 -> 196.78426 | H18: =H15*H16 -> 215.56875 | I18: =I15*I16 -> 234.294 | J18: =J15*J16 -> 252.41326
A19: ASK growth | B19: % | C19: ='05_Historical_Analysis'!K11 -> 0.21765734 | D19: ='05_Historical_Analysis'!L11 -> 0.13065327 | E19: ='05_Historical_Analysis'!M11 -> 0.094603175 | F19: =F18/E18-1 -> 0.044571429 | G19: =G18/F18-1 -> 0.09273523 | H19: =H18/G18-1 -> 0.095457317 | I19: =I18/H18-1 -> 0.086864407 | J19: =J18/I18-1 -> 0.077335526
A20: Capacity identity check | B20: aircraft | C20: =C13-C9-C12 -> 0 | D20: =D13-D9-D12 -> 0 | E20: =E13-E9-E12 -> 0 | F20: =F13-F9-F12 -> 0 | G20: =G13-G9-G12 -> 0 | H20: =H13-H9-H12 -> 0 | I20: =I13-I9-I12 -> 0 | J20: =J13-J9-J12 -> 0
A22: Traffic
A23: Load factor | B23: % | C23: ='03_Raw_Operating_KPIs'!K11 -> 0.85929648 | D23: ='03_Raw_Operating_KPIs'!L11 -> 0.85968254 | E23: ='03_Raw_Operating_KPIs'!M11 -> 0.84396752 | F23: 0.85 | G23: 0.855 | H23: 0.86 | I23: 0.865 | J23: 0.865
A24: RPK | B24: billion | C24: ='03_Raw_Operating_KPIs'!K10 -> 119.7 | D24: ='03_Raw_Operating_KPIs'!L10 -> 135.4 | E24: ='03_Raw_Operating_KPIs'!M10 -> 145.5 | F24: =F18*F23 -> 153.0715 | G24: =G18*G23 -> 168.25054 | H24: =H18*H23 -> 185.38913 | I24: =I18*I23 -> 202.66431 | J24: =J18*J23 -> 218.33747
A25: RPK growth | B25: % | C25: ='05_Historical_Analysis'!K12 -> 0.27476038 | D25: ='05_Historical_Analysis'!L12 -> 0.13116124 | E25: ='05_Historical_Analysis'!M12 -> 0.074593796 | F25: =F24/E24-1 -> 0.052037781 | G25: =G24/F24-1 -> 0.099163084 | H25: =H24/G24-1 -> 0.1018635 | I25: =I24/H24-1 -> 0.093183386 | J25: =J24/I24-1 -> 0.077335526
A26: Passenger distance | B26: 000 km / passenger | C26: =C24/C28 -> 1.1218369 | D26: =D24/D28 -> 1.1416526 | E26: =E24/E28 -> 1.1790924 | F26: =E26*(1+F27) -> 1.2026742 | G26: =F26*(1+G27) -> 1.2267277 | H26: =G26*(1+H27) -> 1.2512623 | I26: =H26*(1+I27) -> 1.2700312 | J26: =I26*(1+J27) -> 1.2890817
A27: Passenger distance growth | B27: % | D27: =D26/C26-1 -> 0.017663608 | E27: =E26/D26-1 -> 0.032794362 | F27: 0.02 | G27: 0.02 | H27: 0.02 | I27: 0.015 | J27: 0.015
A28: Passengers | B28: million | C28: ='03_Raw_Operating_KPIs'!K12 -> 106.7 | D28: ='03_Raw_Operating_KPIs'!L12 -> 118.6 | E28: ='03_Raw_Operating_KPIs'!M12 -> 123.4 | F28: =F24/F26 -> 127.27594 | G28: =G24/G26 -> 137.15394 | H28: =H24/H26 -> 148.16169 | I28: =I24/I26 -> 159.57428 | J28: =J24/J26 -> 169.37442
A29: Passenger growth | B29: % | C29: ='05_Historical_Analysis'!K10 -> 0.24649533 | D29: ='05_Historical_Analysis'!L10 -> 0.11152765 | E29: ='05_Historical_Analysis'!M10 -> 0.040472175 | F29: =F28/E28-1 -> 0.031409589 | G29: =G28/F28-1 -> 0.077610867 | H29: =H28/G28-1 -> 0.080258334 | I29: =I28/H28-1 -> 0.077027966 | J29: =J28/I28-1 -> 0.061414312
A30: Traffic identity check | B30: billion | C30: =C24-C18*C23 -> 0 | D30: =D24-D18*D23 -> 0 | E30: =E24-E18*E23 -> 0 | F30: =F24-F18*F23 -> 0 | G30: =G24-G18*G23 -> 0 | H30: =H24-H18*H23 -> 0 | I30: =I24-I18*I23 -> 0 | J30: =J24-J18*J23 -> 0
A32: Revenue
A33: Yield | B33: INR / passenger km | C33: ='03_Raw_Operating_KPIs'!K15 -> 5.08 | D33: ='03_Raw_Operating_KPIs'!L15 -> 5.15 | E33: ='03_Raw_Operating_KPIs'!M15 -> 5.06 | F33: =E33*(1+F34) -> 5.4648 | G33: =F33*(1+G34) -> 5.656068 | H33: =G33*(1+H34) -> 5.82575 | I33: =H33*(1+I34) -> 5.9713938 | J33: =I33*(1+J34) -> 6.1206786
A34: Yield growth | B34: % | D34: =D33/C33-1 -> 0.013779528 | E34: =E33/D33-1 -> -0.017475728 | F34: 0.08 | G34: 0.035 | H34: 0.03 | I34: 0.025 | J34: 0.025
A35: Passenger PRASK | B35: INR / ASK | C35: =C33*C23 -> 4.3652261 | D35: =D33*D23 -> 4.4273651 | E35: =E33*E23 -> 4.2704756 | F35: =F33*F23 -> 4.64508 | G35: =G33*G23 -> 4.8359381 | H35: =H33*H23 -> 5.010145 | I35: =I33*I23 -> 5.1652556 | J35: =J33*J23 -> 5.294387
A36: Passenger PRASK growth | B36: % | D36: =D35/C35-1 -> 0.01423499 | E36: =E35/D35-1 -> -0.035436301 | F36: =F35/E35-1 -> 0.087719588 | G36: =G35/F35-1 -> 0.041088235 | H36: =H35/G35-1 -> 0.036023392 | I36: =I35/H35-1 -> 0.030959302 | J36: =J35/I35-1 -> 0.025
A37: Ancillary RASK | B37: INR / ASK | C37: =C40/C18/100 -> 0.58124494 | D37: =D40/D18/100 -> 0.70297778 | E37: =E40/E18/100 -> 0.65770882 | F37: =F40/F18/100 -> 0.68189261 | G37: =G40/G18/100 -> 0.70607738 | H37: =H40/H18/100 -> 0.72761351 | I37: =I40/I18/100 -> 0.74986953 | J37: =J40/J18/100 -> 0.76833923
A38: RASK - CASK spread | B38: INR / ASK | C38: =C44-C57 -> 0.57042096 | D38: =D44-D57 -> 0.46702222 | E38: =E44-E57 -> -0.064506961 | F38: =F44-F57 -> 0.014246626 | G38: =G44-G57 -> 0.10956006 | H38: =H44-H57 -> 0.15748341 | I38: =I44-I57 -> 0.18289885 | J38: =J44-J57 -> 0.19507738
A39: Passenger revenue | B39: INR crore | C39: =C24*C33*100 -> 60807.6 | D39: =D24*D33*100 -> 69731 | E39: =E24*E33*100 -> 73623 | F39: =F24*F33*100 -> 83650.512 | G39: =G24*G33*100 -> 95163.649 | H39: =H24*H33*100 -> 108003.07 | I39: =I24*I33*100 -> 121018.84 | J39: =J24*J33*100 -> 133637.35
A40: Ancillary and other operating revenue | B40: INR crore | C40: =C43-C39 -> 8096.742 | D40: =D43-D39 -> 11071.9 | E40: =E43-E39 -> 11338.9 | F40: =F28*F41/10 -> 12279.803 | G40: =G28*G41/10 -> 13894.491 | H40: =H28*H41/10 -> 15685.074 | I40: =I28*I41/10 -> 17568.994 | J40: =J28*J41/10 -> 19393.901
A41: Ancillary revenue / passenger | B41: INR / passenger | C41: =C40*10/C28 -> 758.83243 | D41: =D40*10/D28 -> 933.54975 | E41: =E40*10/E28 -> 918.87358 | F41: =E41*(1+F42) -> 964.81726 | G41: =F41*(1+G42) -> 1013.0581 | H41: =G41*(1+H42) -> 1058.6457 | I41: =H41*(1+I42) -> 1100.9916 | J41: =I41*(1+J42) -> 1145.0312
A42: Ancillary revenue / passenger growth | B42: % | D42: =D41/C41-1 -> 0.23024493 | E42: =E41/D41-1 -> -0.015720818 | F42: 0.05 | G42: 0.05 | H42: 0.045 | I42: 0.04 | J42: 0.04
A43: Revenue from operations | B43: INR crore | C43: ='02_Raw_Financials'!K8 -> 68904.342 | D43: ='02_Raw_Financials'!L8 -> 80802.9 | E43: ='02_Raw_Financials'!M8 -> 84961.9 | F43: =F39+F40 -> 95930.314 | G43: =G39+G40 -> 109058.14 | H43: =H39+H40 -> 123688.15 | I43: =I39+I40 -> 138587.84 | J43: =J39+J40 -> 153031.25
A44: Calculated RASK | B44: INR / ASK | C44: =C35+C37 -> 4.9464711 | D44: =D35+D37 -> 5.1303429 | E44: =E35+E37 -> 4.9281845 | F44: =F35+F37 -> 5.3269726 | G44: =G35+G37 -> 5.5420155 | H44: =H35+H37 -> 5.7377585 | I44: =I35+I37 -> 5.9151252 | J44: =J35+J37 -> 6.0627262
A45: Reported RASK | B45: INR / ASK | C45: ='03_Raw_Operating_KPIs'!K16 -> 4.96 | D45: ='03_Raw_Operating_KPIs'!L16 -> 5.14 | E45: ='03_Raw_Operating_KPIs'!M16 -> 4.99
A46: RASK definition difference | B46: INR / ASK | C46: =C44-C45 -> -0.01352893 | D46: =D44-D45 -> -0.0096571429 | E46: =E44-E45 -> -0.061815545
A47: Revenue identity check | B47: INR crore | C47: =C43-C39-C40 -> 0 | D47: =D43-D39-D40 -> 0 | E47: =E43-E39-E40 -> 0 | F47: =F43-F39-F40 -> 0 | G47: =G43-G39-G40 -> 0 | H47: =H43-H39-H40 -> 0 | I47: =I43-I39-I40 -> 0 | J47: =J43-J39-J40 -> 0
A48: Revenue growth | B48: % | D48: =D43/C43-1 -> 0.17268227 | E48: =E43/D43-1 -> 0.051470925 | F48: =F43/E43-1 -> 0.12909804 | G48: =G43/F43-1 -> 0.13684752 | H48: =H43/G43-1 -> 0.13414868 | I48: =I43/H43-1 -> 0.12046175 | J48: =J43/I43-1 -> 0.10421846
A50: Cost and Profitability
A51: Fuel CASK | B51: INR / ASK | C51: ='02_Raw_Financials'!K11/('03_Raw_Operating_KPIs'!K9*100) -> 1.7160501 | D51: ='02_Raw_Financials'!L11/('03_Raw_Operating_KPIs'!L9*100) -> 1.6633206 | E51: ='02_Raw_Financials'!M11/('03_Raw_Operating_KPIs'!M9*100) -> 1.4726914 | F51: =E51*(1+F52) -> 1.546326 | G51: =F51*(1+G52) -> 1.5153995 | H51: =G51*(1+H52) -> 1.5457075 | I51: =H51*(1+I52) -> 1.5766216 | J51: =I51*(1+J52) -> 1.608154
A52: Fuel CASK growth | B52: % | D52: =D51/C51-1 -> -0.030727234 | E52: =E51/D51-1 -> -0.11460762 | F52: 0.05 | G52: -0.02 | H52: 0.02 | I52: 0.02 | J52: 0.02
A53: Fuel cost | B53: INR crore | C53: =C18*C51*100 -> 23904.578 | D53: =D18*D51*100 -> 26197.3 | E53: =E18*E51*100 -> 25389.2 | F53: =F18*F51*100 -> 27846.875 | G53: =G18*G51*100 -> 29820.676 | H53: =H18*H51*100 -> 33320.623 | I53: =I18*I51*100 -> 36939.299 | J53: =J18*J51*100 -> 40591.94
A54: Ex-fuel CASK (including FX) | B54: INR / ASK | C54: ='03_Raw_Operating_KPIs'!K18 -> 2.66 | D54: ='03_Raw_Operating_KPIs'!L18 -> 3 | E54: ='03_Raw_Operating_KPIs'!M18 -> 3.52 | F54: =E54*(1+F55) -> 3.7664 | G54: =F54*(1+G55) -> 3.917056 | H54: =G54*(1+H55) -> 4.0345677 | I54: =H54*(1+I55) -> 4.1556047 | J54: =I54*(1+J55) -> 4.2594948
A55: Ex-fuel CASK growth (including FX) | B55: % | D55: =D54/C54-1 -> 0.12781955 | E55: =E54/D54-1 -> 0.17333333 | F55: 0.07 | G55: 0.04 | H55: 0.03 | I55: 0.03 | J55: 0.025
A56: Ex-fuel cost | B56: INR crore | C56: =C18*C54*100 -> 37053.8 | D56: =D18*D54*100 -> 47250 | E56: =E18*E54*100 -> 60684.8 | F56: =F18*F54*100 -> 67826.881 | G56: =G18*G54*100 -> 77081.495 | H56: =H18*H54*100 -> 86972.672 | I56: =I18*I54*100 -> 97363.327 | J56: =J18*J54*100 -> 107515.3
A57: Total CASK | B57: INR / ASK | C57: =C51+C54 -> 4.3760501 | D57: =D51+D54 -> 4.6633206 | E57: =E51+E54 -> 4.9926914 | F57: =F51+F54 -> 5.312726 | G57: =G51+G54 -> 5.4324555 | H57: =H51+H54 -> 5.5802751 | I57: =I51+I54 -> 5.7322263 | J57: =J51+J54 -> 5.8676489
A58: Total operating cost | B58: INR crore | C58: =C53+C56 -> 60958.378 | D58: =D53+D56 -> 73447.3 | E58: =E53+E56 -> 86074 | F58: =F53+F56 -> 95673.755 | G58: =G53+G56 -> 106902.17 | H58: =H53+H56 -> 120293.3 | I58: =I53+I56 -> 134302.63 | J58: =J53+J56 -> 148107.24
A59: Operating result before other income | B59: INR crore | C59: =C43-C58 -> 7945.964 | D59: =D43-D58 -> 7355.6 | E59: =E43-E58 -> -1112.1 | F59: =F43-F58 -> 256.5591 | G59: =G43-G58 -> 2155.9694 | H59: =H43-H58 -> 3394.8503 | I59: =I43-I58 -> 4285.2104 | J59: =J43-J58 -> 4924.0117
A60: Other income | B60: INR crore | C60: ='02_Raw_Financials'!K9 -> 2326.821 | D60: ='02_Raw_Financials'!L9 -> 3295.3 | E60: ='02_Raw_Financials'!M9 -> 4551.5 | F60: =F43*F61 -> 3837.2126 | G60: =G43*G61 -> 4144.2093 | H60: =H43*H61 -> 4329.0851 | I60: =I43*I61 -> 4573.3986 | J60: =J43*J61 -> 4590.9374
A61: Other income / revenue | B61: % | C61: =C60/C43 -> 0.033768859 | D61: =D60/D43 -> 0.040781952 | E61: =E60/E43 -> 0.053571071 | F61: 0.04 | G61: 0.038 | H61: 0.035 | I61: 0.033 | J61: 0.03
A62: Reported CASK / EBIT reconciliation | B62: INR crore | C62: =C63-C59-C60 -> 1099.423 | D62: =D63-D59-D60 -> 900.7 | E62: =E63-E59-E60 -> -815.7 | F62: 0 | G62: 0 | H62: 0 | I62: 0 | J62: 0
A63: EBIT | B63: INR crore | C63: ='05_Historical_Analysis'!K68 -> 11372.208 | D63: ='05_Historical_Analysis'!L68 -> 11551.6 | E63: ='05_Historical_Analysis'!M68 -> 2623.7 | F63: =F59+F60+F62 -> 4093.7717 | G63: =G59+G60+G62 -> 6300.1788 | H63: =H59+H60+H62 -> 7723.9354 | I63: =I59+I60+I62 -> 8858.609 | J63: =J59+J60+J62 -> 9514.9491
A64: EBIT margin | B64: % | C64: =C63/C43 -> 0.16504342 | D64: =D63/D43 -> 0.14296022 | E64: =E63/E43 -> 0.030880901 | F64: =F63/F43 -> 0.042674432 | G64: =G63/G43 -> 0.057768992 | H64: =H63/H43 -> 0.062446852 | I64: =I63/I43 -> 0.063920537 | J64: =J63/J43 -> 0.062176512
A65: Depreciation and amortisation / ASK | B65: INR / ASK | C65: =C67/C18/100 -> 0.46128708 | D65: =D67/D18/100 -> 0.55112381 | E65: =E67/E18/100 -> 0.62692575 | F65: =E65*(1+F66) -> 0.63946427 | G65: =F65*(1+G66) -> 0.6586482 | H65: =G65*(1+H66) -> 0.67840764 | I65: =H65*(1+I66) -> 0.69536783 | J65: =I65*(1+J66) -> 0.71275203
A66: D&A / ASK growth | B66: % | D66: =D65/C65-1 -> 0.19475233 | E66: =E65/D65-1 -> 0.13754068 | F66: 0.02 | G66: 0.03 | H66: 0.03 | I66: 0.025 | J66: 0.025
A67: Depreciation and amortisation | B67: INR crore | C67: ='02_Raw_Financials'!K20 -> 6425.729 | D67: ='02_Raw_Financials'!L20 -> 8680.2 | E67: ='02_Raw_Financials'!M20 -> 10808.2 | F67: =F18*F65*100 -> 11515.736 | G67: =G18*G65*100 -> 12961.16 | H67: =H18*H65*100 -> 14624.349 | I67: =I18*I65*100 -> 16292.051 | J67: =J18*J65*100 -> 17990.806
A68: EBITDA | B68: INR crore | C68: ='05_Historical_Analysis'!K69 -> 17797.937 | D68: ='05_Historical_Analysis'!L69 -> 20231.8 | E68: ='05_Historical_Analysis'!M69 -> 13431.9 | F68: =F63+F67 -> 15609.507 | G68: =G63+G67 -> 19261.338 | H68: =H63+H67 -> 22348.284 | I68: =I63+I67 -> 25150.66 | J68: =J63+J67 -> 27505.755
A69: EBITDA margin | B69: % | C69: =C68/C43 -> 0.25829921 | D69: =D68/D43 -> 0.25038458 | E69: =E68/E43 -> 0.15809322 | F69: =F68/F43 -> 0.16271715 | G69: =G68/G43 -> 0.17661532 | H69: =H68/H43 -> 0.18068251 | I69: =I68/I43 -> 0.18147812 | J69: =J68/J43 -> 0.17973947
A70: Aircraft rentals / ASK | B70: INR / ASK | C70: =C72/C18/100 -> 0.077185571 | D70: =D72/D18/100 -> 0.19113016 | E70: =E72/E18/100 -> 0.12092227 | F70: =E70*(1+F71) -> 0.11487616 | G70: =F70*(1+G71) -> 0.10913235 | H70: =G70*(1+H71) -> 0.10367573 | I70: =H70*(1+I71) -> 0.098491948 | J70: =I70*(1+J71) -> 0.09356735
A71: Aircraft rentals / ASK growth | B71: % | D71: =D70/C70-1 -> 1.4762421 | E71: =E70/D70-1 -> -0.36733023 | F71: -0.05 | G71: -0.05 | H71: -0.05 | I71: -0.05 | J71: -0.05
A72: Aircraft and engine rentals | B72: INR crore | C72: ='02_Raw_Financials'!K12 -> 1075.195 | D72: ='02_Raw_Financials'!L12 -> 3010.3 | E72: ='02_Raw_Financials'!M12 -> 2084.7 | F72: =F18*F70*100 -> 2068.7372 | G72: =G18*G70*100 -> 2147.5529 | H72: =H18*H70*100 -> 2234.9249 | I72: =I18*I70*100 -> 2307.6073 | J72: =J18*J70*100 -> 2361.7639
A73: EBITDAR proxy | B73: INR crore | C73: ='05_Historical_Analysis'!K70 -> 18873.132 | D73: ='05_Historical_Analysis'!L70 -> 23242.1 | E73: ='05_Historical_Analysis'!M70 -> 15516.6 | F73: =F68+F72 -> 17678.244 | G73: =G68+G72 -> 21408.891 | H73: =H68+H72 -> 24583.209 | I73: =I68+I72 -> 27458.268 | J73: =J68+J72 -> 29867.519
A74: EBITDAR margin | B74: % | C74: =C73/C43 -> 0.27390338 | D74: =D73/D43 -> 0.28763943 | E74: =E73/E43 -> 0.1826301 | F74: =F73/F43 -> 0.18428215 | G74: =G73/G43 -> 0.19630714 | H74: =H73/H43 -> 0.19875154 | I74: =I73/I43 -> 0.19812899 | J74: =J73/J43 -> 0.19517268
A75: EBIT identity check | B75: INR crore | C75: =C63-C59-C60-C62 -> 0 | D75: =D63-D59-D60-D62 -> 0 | E75: =E63-E59-E60-E62 -> 0 | F75: =F63-F59-F60-F62 -> 0 | G75: =G63-G59-G60-G62 -> 0 | H75: =H63-H59-H60-H62 -> 0 | I75: =I63-I59-I60-I62 -> 0 | J75: =J63-J59-J60-J62 -> 9.094947e-13
A76: EBITDA identity check | B76: INR crore | C76: =C68-C63-C67 -> 0 | D76: =D68-D63-D67 -> 0 | E76: =E68-E63-E67 -> 0 | F76: =F68-F63-F67 -> 0 | G76: =G68-G63-G67 -> 0 | H76: =H68-H63-H67 -> 0 | I76: =I68-I63-I67 -> 0 | J76: =J68-J63-J67 -> 0
A77: Operating cost identity check | B77: INR crore | C77: =C58-C53-C56 -> 0 | D77: =D58-D53-D56 -> 0 | E77: =E58-E53-E56 -> 0 | F77: =F58-F53-F56 -> 0 | G77: =G58-G53-G56 -> 0 | H77: =H58-H53-H56 -> 0 | I77: =I58-I53-I56 -> 0 | J77: =J58-J53-J56 -> 0
A80: Management Commentary and Near-Term Outlook
A81: Topic | B81: Classification | C81: Management statement
A82: Q1 FY2027 capacity growth | B82: Management outlook | C82: 3%-4% year-on-year; no full-year capacity guidance provided.
A83: Q1 FY2027 PRASK growth | B83: Management outlook | C83: Mid-teens year-on-year; all-in PRASK including the fuel surcharge.
A84: CASK ex-fuel ex-FX | B84: Directional outlook | C84: Mid- to high-single-digit increase over coming quarters; highly conditional.
A85: Fuel hedging | B85: Management commentary | C85: Not implemented; only in early internal evaluation.
A86: Currency hedges in place | B86: Reported position | C86: Approximately US$1.3 billion hedged as of the earnings call.
A87: Currency hedge policy | B87: Management policy | C87: Target increased to US$3.0 billion: US$1.0 billion over 12 months and US$2.0 billion across years 2-5.
A88: USD/INR MTM sensitivity | B88: Management sensitivity | C88: Approximately INR 900 crore for each INR 1 depreciation against the US dollar.
A90: Fuel CASK timing | B90: Management commentary | C90: Approximately one-month lag from benchmark fuel prices and currency movements.
A91: Fuel-cost pass-through | B91: Management commentary | C91: Large part recovered domestically; international increase not fully recovered.
A92: P&W AOG aircraft | B92: Management outlook | C92: Currently in the 40s and expected to decline into the 30s by year-end.
A93: Fleet strategy | B93: Management commentary | C93: No order-book delivery change; return most damp leases and reduce older-aircraft use.
... A96: Source | B96: Document | C96: InterGlobe Aviation Q4 FY2026 Earnings Call Transcript

Sheet 07_Income_Statement
A1: Forecast Income Statement
A2: InterGlobe Aviation Limited | INR crore | FY2024A-FY2031E
A3: Base case linked to the operating model; finance costs are based on average lease-adjusted debt.
A5: Metric | B5: Unit | C5: FY2024A | D5: FY2025A | E5: FY2026A | F5: FY2027E | G5: FY2028E | H5: FY2029E | I5: FY2030E | J5: FY2031E
A6: Period | C6: Actual | D6: Actual | E6: Actual | F6: Forecast | G6: Forecast | H6: Forecast | I6: Forecast | J6: Forecast
A8: Revenue
A9: Passenger revenue | B9: INR crore | C9: ='06_Operating_Model'!C39 -> 60807.6 | D9: ='06_Operating_Model'!D39 -> 69731 | E9: ='06_Operating_Model'!E39 -> 73623 | F9: ='06_Operating_Model'!F39 -> 83650.512 | G9: ='06_Operating_Model'!G39 -> 95163.649 | H9: ='06_Operating_Model'!H39 -> 108003.07 | I9: ='06_Operating_Model'!I39 -> 121018.84 | J9: ='06_Operating_Model'!J39 -> 133637.35
A10: Ancillary and other operating revenue | B10: INR crore | C10: ='06_Operating_Model'!C40 -> 8096.742 | D10: ='06_Operating_Model'!D40 -> 11071.9 | E10: ='06_Operating_Model'!E40 -> 11338.9 | F10: ='06_Operating_Model'!F40 -> 12279.803 | G10: ='06_Operating_Model'!G40 -> 13894.491 | H10: ='06_Operating_Model'!H40 -> 15685.074 | I10: ='06_Operating_Model'!I40 -> 17568.994 | J10: ='06_Operating_Model'!J40 -> 19393.901
A11: Revenue from operations | B11: INR crore | C11: ='06_Operating_Model'!C43 -> 68904.342 | D11: ='06_Operating_Model'!D43 -> 80802.9 | E11: ='06_Operating_Model'!E43 -> 84961.9 | F11: ='06_Operating_Model'!F43 -> 95930.314 | G11: ='06_Operating_Model'!G43 -> 109058.14 | H11: ='06_Operating_Model'!H43 -> 123688.15 | I11: ='06_Operating_Model'!I43 -> 138587.84 | J11: ='06_Operating_Model'!J43 -> 153031.25
A12: Revenue growth | B12: % | D12: ='06_Operating_Model'!D48 -> 0.17268227 | E12: ='06_Operating_Model'!E48 -> 0.051470925 | F12: ='06_Operating_Model'!F48 -> 0.12909804 | G12: ='06_Operating_Model'!G48 -> 0.13684752 | H12: ='06_Operating_Model'!H48 -> 0.13414868 | I12: ='06_Operating_Model'!I48 -> 0.12046175 | J12: ='06_Operating_Model'!J48 -> 0.10421846
A13: Other income | B13: INR crore | C13: ='06_Operating_Model'!C60 -> 2326.821 | D13: ='06_Operating_Model'!D60 -> 3295.3 | E13: ='06_Operating_Model'!E60 -> 4551.5 | F13: ='06_Operating_Model'!F60 -> 3837.2126 | G13: ='06_Operating_Model'!G60 -> 4144.2093 | H13: ='06_Operating_Model'!H60 -> 4329.0851 | I13: ='06_Operating_Model'!I60 -> 4573.3986 | J13: ='06_Operating_Model'!J60 -> 4590.9374
A14: Total income | B14: INR crore | C14: =C11+C13 -> 71231.163 | D14: =D11+D13 -> 84098.2 | E14: =E11+E13 -> 89513.4 | F14: =F11+F13 -> 99767.527 | G14: =G11+G13 -> 113202.35 | H14: =H11+H13 -> 128017.23 | I14: =I11+I13 -> 143161.24 | J14: =J11+J13 -> 157622.18
A16: Operating Expenses and Profitability
A17: Aircraft fuel expense | B17: INR crore | C17: ='02_Raw_Financials'!K11 -> 23904.578 | D17: ='02_Raw_Financials'!L11 -> 26197.3 | E17: ='02_Raw_Financials'!M11 -> 25389.2 | F17: ='06_Operating_Model'!F53 -> 27846.875 | G17: ='06_Operating_Model'!G53 -> 29820.676 | H17: ='06_Operating_Model'!H53 -> 33320.623 | I17: ='06_Operating_Model'!I53 -> 36939.299 | J17: ='06_Operating_Model'!J53 -> 40591.94
A18: Aircraft and engine rentals | B18: INR crore | C18: ='02_Raw_Financials'!K12 -> 1075.195 | D18: ='02_Raw_Financials'!L12 -> 3010.3 | E18: ='02_Raw_Financials'!M12 -> 2084.7 | F18: ='06_Operating_Model'!F72 -> 2068.7372 | G18: ='06_Operating_Model'!G72 -> 2147.5529 | H18: ='06_Operating_Model'!H72 -> 2234.9249 | I18: ='06_Operating_Model'!I72 -> 2307.6073 | J18: ='06_Operating_Model'!J72 -> 2361.7639
A19: Other ex-fuel operating expenses | B19: INR crore | C19: =SUM('02_Raw_Financials'!K13:K19) -> 27606.998 | D19: =SUM('02_Raw_Financials'!L13:L19) -> 33537 | E19: =SUM('02_Raw_Financials'!M13:M19) -> 45504.6 | F19: ='06_Operating_Model'!F56-F18-F20 -> 54242.408 | G19: ='06_Operating_Model'!G56-G18-G20 -> 61972.783 | H19: ='06_Operating_Model'!H56-H18-H20 -> 70113.399 | I19: ='06_Operating_Model'!I56-I18-I20 -> 78763.668 | J19: ='06_Operating_Model'!J56-J18-J20 -> 87162.726
A20: Depreciation and amortisation | B20: INR crore | C20: ='02_Raw_Financials'!K20 -> 6425.729 | D20: ='02_Raw_Financials'!L20 -> 8680.2 | E20: ='02_Raw_Financials'!M20 -> 10808.2 | F20: ='06_Operating_Model'!F67 -> 11515.736 | G20: ='06_Operating_Model'!G67 -> 12961.16 | H20: ='06_Operating_Model'!H67 -> 14624.349 | I20: ='06_Operating_Model'!I67 -> 16292.051 | J20: ='06_Operating_Model'!J67 -> 17990.806
A21: Total operating expenses | B21: INR crore | C21: =SUM(C17:C20) -> 59012.5 | D21: =SUM(D17:D20) -> 71424.8 | E21: =SUM(E17:E20) -> 83786.7 | F21: =SUM(F17:F20) -> 95673.755 | G21: =SUM(G17:G20) -> 106902.17 | H21: =SUM(H17:H20) -> 120293.3 | I21: =SUM(I17:I20) -> 134302.63 | J21: =SUM(J17:J20) -> 148107.24
A22: EBIT before adjustment | B22: INR crore | C22: =C14-C21 -> 12218.663 | D22: =D14-D21 -> 12673.4 | E22: =E14-E21 -> 5726.7 | F22: =F14-F21 -> 4093.7717 | G22: =G14-G21 -> 6300.1788 | H22: =H14-H21 -> 7723.9354 | I22: =I14-I21 -> 8858.609 | J22: =J14-J21 -> 9514.9491
A23: Reported CASK / EBIT reconciliation | B23: INR crore | C23: ='06_Operating_Model'!C63-C22 -> -846.455 | D23: ='06_Operating_Model'!D63-D22 -> -1121.8 | E23: ='06_Operating_Model'!E63-E22 -> -3103 | F23: ='06_Operating_Model'!F63-F22 -> 0 | G23: ='06_Operating_Model'!G63-G22 -> -7.2759576e-12 | H23: ='06_Operating_Model'!H63-H22 -> 1.9099389e-11 | I23: ='06_Operating_Model'!I63-I22 -> -2.7284841e-11 | J23: ='06_Operating_Model'!J63-J22 -> 0
A24: Standardised EBIT | B24: INR crore | C24: =C22+C23 -> 11372.208 | D24: =D22+D23 -> 11551.6 | E24: =E22+E23 -> 2623.7 | F24: =F22+F23 -> 4093.7717 | G24: =G22+G23 -> 6300.1788 | H24: =H22+H23 -> 7723.9354 | I24: =I22+I23 -> 8858.609 | J24: =J22+J23 -> 9514.9491
A25: EBIT margin | B25: % | C25: =C24/C11 -> 0.16504342 | D25: =D24/D11 -> 0.14296022 | E25: =E24/E11 -> 0.030880901 | F25: =F24/F11 -> 0.042674432 | G25: =G24/G11 -> 0.057768992 | H25: =H24/H11 -> 0.062446852 | I25: =I24/I11 -> 0.063920537 | J25: =J24/J11 -> 0.062176512
A26: EBITDA | B26: INR crore | C26: =C24+C20 -> 17797.937 | D26: =D24+D20 -> 20231.8 | E26: =E24+E20 -> 13431.9 | F26: =F24+F20 -> 15609.507 | G26: =G24+G20 -> 19261.338 | H26: =H24+H20 -> 22348.284 | I26: =I24+I20 -> 25150.66 | J26: =J24+J20 -> 27505.755
A27: EBITDA margin | B27: % | C27: =C26/C11 -> 0.25829921 | D27: =D26/D11 -> 0.25038458 | E27: =E26/E11 -> 0.15809322 | F27: =F26/F11 -> 0.16271715 | G27: =G26/G11 -> 0.17661532 | H27: =H26/H11 -> 0.18068251 | I27: =I26/I11 -> 0.18147812 | J27: =J26/J11 -> 0.17973947
A28: EBITDAR | B28: INR crore | C28: =C26+C18 -> 18873.132 | D28: =D26+D18 -> 23242.1 | E28: =E26+E18 -> 15516.6 | F28: =F26+F18 -> 17678.244 | G28: =G26+G18 -> 21408.891 | H28: =H26+H18 -> 24583.209 | I28: =I26+I18 -> 27458.268 | J28: =J26+J18 -> 29867.519
A29: EBITDAR margin | B29: % | C29: =C28/C11 -> 0.27390338 | D29: =D28/D11 -> 0.28763943 | E29: =E28/E11 -> 0.1826301 | F29: =F28/F11 -> 0.18428215 | G29: =G28/G11 -> 0.19630714 | H29: =H28/H11 -> 0.19875154 | I29: =I28/I11 -> 0.19812899 | J29: =J28/J11 -> 0.19517268
A31: Below-the-Line Items
A32: Finance costs | B32: INR crore | C32: ='02_Raw_Financials'!K21 -> 4169.354 | D32: ='02_Raw_Financials'!L21 -> 5080 | E32: ='02_Raw_Financials'!M21 -> 5890.8 | F32: ='08_Balance_Sheet'!F77 -> 6219.936 | G32: ='08_Balance_Sheet'!G77 -> 6020.011 | H32: ='08_Balance_Sheet'!H77 -> 5779.7262 | I32: ='08_Balance_Sheet'!I77 -> 5661.6 | J32: ='08_Balance_Sheet'!J77 -> 5689.2306
A33: Finance costs / revenue | B33: % | C33: =C32/C11 -> 0.060509307 | D33: =D32/D11 -> 0.062869031 | E33: =E32/E11 -> 0.069334608 | F33: =F32/F11 -> 0.064838065 | G33: =G32/G11 -> 0.055200015 | H33: =H32/H11 -> 0.046728214 | I33: =I32/I11 -> 0.04085207 | J33: =J32/J11 -> 0.037176922
A34: Exceptional items | B34: INR crore | C34: ='02_Raw_Financials'!K23 -> 0 | D34: ='02_Raw_Financials'!L23 -> 0 | E34: ='02_Raw_Financials'!M23 -> 1796.4 | F34: 0 | G34: 0 | H34: 0 | I34: 0 | J34: 0
A35: Profit before tax | B35: INR crore | C35: ='02_Raw_Financials'!K24 -> 8049.309 | D35: ='02_Raw_Financials'!L24 -> 7593.4 | E35: ='02_Raw_Financials'!M24 -> -1960.5 | F35: =F24-F32-F34 -> -2126.1643 | G35: =G24-G32-G34 -> 280.16777 | H35: =H24-H32-H34 -> 1944.2092 | I35: =I24-I32-I34 -> 3197.009 | J35: =J24-J32-J34 -> 3825.7185
A36: Effective tax rate | B36: % | C36: =IF(C35=0,0,C37/C35) -> -0.015300568 | D36: =IF(D35=0,0,D37/D35) -> 0.04411726 | E36: =IF(E35=0,0,E37/E35) -> -0.22091303 | F36: 0.252 | G36: 0.252 | H36: 0.252 | I36: 0.252 | J36: 0.252
A37: Tax expense | B37: INR crore | C37: ='02_Raw_Financials'!K25 -> -123.159 | D37: ='02_Raw_Financials'!L25 -> 335 | E37: ='02_Raw_Financials'!M25 -> 433.1 | F37: =MAX(F35,0)*F36 -> 0 | G37: =MAX(G35,0)*G36 -> 70.602278 | H37: =MAX(H35,0)*H36 -> 489.94072 | I37: =MAX(I35,0)*I36 -> 805.64626 | J37: =MAX(J35,0)*J36 -> 964.08105
A38: Profit after tax | B38: INR crore | C38: ='02_Raw_Financials'!K26 -> 8172.468 | D38: ='02_Raw_Financials'!L26 -> 7258.4 | E38: ='02_Raw_Financials'!M26 -> -2393.6 | F38: =F35-F37 -> -2126.1643 | G38: =G35-G37 -> 209.56549 | H38: =H35-H37 -> 1454.2685 | I38: =I35-I37 -> 2391.3627 | J38: =J35-J37 -> 2861.6374
A39: PAT margin | B39: % | C39: =C38/C11 -> 0.11860599 | D39: =D38/D11 -> 0.089828459 | E39: =E38/E11 -> -0.028172628 | F39: =F38/F11 -> -0.022163633 | G39: =G38/G11 -> 0.0019215942 | H39: =H38/H11 -> 0.011757541 | I39: =I38/I11 -> 0.017255214 | J39: =J38/J11 -> 0.018699694
A41: Per Share
A42: Diluted weighted average shares | B42: crore shares | C42: ='02_Raw_Financials'!K26/'02_Raw_Financials'!K28 -> 38.620424 | D42: ='02_Raw_Financials'!L26/'02_Raw_Financials'!L28 -> 38.6764 | E42: ='02_Raw_Financials'!M26/'02_Raw_Financials'!M28 -> 38.681319 | F42: =E42*(1+F43) -> 38.681319 | G42: =F42*(1+G43) -> 38.681319 | H42: =G42*(1+H43) -> 38.681319 | I42: =H42*(1+I43) -> 38.681319 | J42: =I42*(1+J43) -> 38.681319
A43: Share count growth | B43: % | D43: =D42/C42-1 -> 0.0014493807 | E43: =E42/D42-1 -> 0.00012717361 | F43: 0 | G43: 0 | H43: 0 | I43: 0 | J43: 0
A44: Diluted EPS | B44: INR per share | C44: ='02_Raw_Financials'!K28 -> 211.61 | D44: ='02_Raw_Financials'!L28 -> 187.67 | E44: ='02_Raw_Financials'!M28 -> -61.88 | F44: =F38/F42 -> -54.96618 | G44: =G38/G42 -> 5.4177443 | H44: =H38/H42 -> 37.596146 | I44: =I38/I42 -> 61.822161 | J44: =J38/J42 -> 73.979831
A45: EPS growth | B45: % | D45: =IF(C44=0,0,D44/C44-1) -> -0.11313265 | E45: =IF(D44=0,0,E44/D44-1) -> -1.3297277 | F45: =IF(E44=0,0,F44/E44-1) -> -0.11172948 | G45: =IF(F44=0,0,G44/F44-1) -> -1.098565 | H45: =IF(G44=0,0,H44/G44-1) -> 5.9394464 | I45: =IF(H44=0,0,I44/H44-1) -> 0.64437496 | J45: =IF(I44=0,0,J44/I44-1) -> 0.19665553
A47: Reconciliations
A48: Income statement identity check | B48: INR crore | C48: =C14-C21-C32-C34-C35 -> 0 | D48: =D14-D21-D32-D34-D35 -> 0 | E48: =E14-E21-E32-E34-E35 -> -3.1832315e-12 | F48: =F14-F21-F32-F34-F35 -> 0 | G48: =G14-G21-G32-G34-G35 -> 7.2759576e-12 | H48: =H14-H21-H32-H34-H35 -> -1.9099389e-11 | I48: =I14-I21-I32-I34-I35 -> 2.7284841e-11 | J48: =J14-J21-J32-J34-J35 -> 0
A49: PAT identity check | B49: INR crore | C49: =C35-C37-C38 -> 0 | D49: =D35-D37-D38 -> 0 | E49: =E35-E37-E38 -> 0 | F49: =F35-F37-F38 -> 0 | G49: =G35-G37-G38 -> 0 | H49: =H35-H37-H38 -> 0 | I49: =I35-I37-I38 -> 0 | J49: =J35-J37-J38 -> 0

Sheet 08_Balance_Sheet
A1: Balance Sheet: Fleet and Lease Schedules
A2: InterGlobe Aviation Limited | INR crore unless stated | FY2024A-FY2031E
A3: Fleet, leases, working capital and finance schedules supporting cash flow and valuation.
A5: Metric | B5: Unit | C5: FY2024A | D5: FY2025A | E5: FY2026A | F5: FY2027E | G5: FY2028E | H5: FY2029E | I5: FY2030E | J5: FY2031E
A6: Period | C6: Actual | D6: Actual | E6: Actual | F6: Forecast | G6: Forecast | H6: Forecast | I6: Forecast | J6: Forecast
A8: Fleet Bridge
A9: Beginning fleet | B9: aircraft | C9: ='06_Operating_Model'!C9 -> 304 | D9: ='06_Operating_Model'!D9 -> 367 | E9: ='06_Operating_Model'!E9 -> 434 | F9: ='06_Operating_Model'!F9 -> 441 | G9: ='06_Operating_Model'!G9 -> 473 | H9: ='06_Operating_Model'!H9 -> 511 | I9: ='06_Operating_Model'!I9 -> 551 | J9: ='06_Operating_Model'!J9 -> 589
A10: Aircraft deliveries | B10: aircraft | E10: 72 | F10: ='06_Operating_Model'!F10 -> 42 | G10: ='06_Operating_Model'!G10 -> 46 | H10: ='06_Operating_Model'!H10 -> 48 | I10: ='06_Operating_Model'!I10 -> 48 | J10: ='06_Operating_Model'!J10 -> 45
A11: Aircraft retirements | B11: aircraft | E11: 65 | F11: ='06_Operating_Model'!F11 -> 10 | G11: ='06_Operating_Model'!G11 -> 8 | H11: ='06_Operating_Model'!H11 -> 8 | I11: ='06_Operating_Model'!I11 -> 10 | J11: ='06_Operating_Model'!J11 -> 10
A12: Net fleet additions | B12: aircraft | C12: ='06_Operating_Model'!C12 -> 63 | D12: ='06_Operating_Model'!D12 -> 67 | E12: ='06_Operating_Model'!E12 -> 7 | F12: =F10-F11 -> 32 | G12: =G10-G11 -> 38 | H12: =H10-H11 -> 40 | I12: =I10-I11 -> 38 | J12: =J10-J11 -> 35
A13: Ending fleet | B13: aircraft | C13: ='06_Operating_Model'!C13 -> 367 | D13: ='06_Operating_Model'!D13 -> 434 | E13: ='06_Operating_Model'!E13 -> 441 | F13: ='06_Operating_Model'!F13 -> 473 | G13: ='06_Operating_Model'!G13 -> 511 | H13: ='06_Operating_Model'!H13 -> 551 | I13: ='06_Operating_Model'!I13 -> 589 | J13: ='06_Operating_Model'!J13 -> 624
A14: Fleet growth | B14: % | C14: ='06_Operating_Model'!C14 -> 0.20723684 | D14: ='06_Operating_Model'!D14 -> 0.18256131 | E14: ='06_Operating_Model'!E14 -> 0.016129032 | F14: ='06_Operating_Model'!F14 -> 0.072562358 | G14: ='06_Operating_Model'!G14 -> 0.080338266 | H14: ='06_Operating_Model'!H14 -> 0.078277886 | I14: ='06_Operating_Model'!I14 -> 0.068965517 | J14: ='06_Operating_Model'!J14 -> 0.05942275
A15: Fleet identity check | B15: aircraft | C15: =C13-C9-C12 -> 0 | D15: =D13-D9-D12 -> 0 | E15: =E13-E9-E12 -> 0 | F15: =F13-F9-F12 -> 0 | G15: =G13-G9-G12 -> 0 | H15: =H13-H9-H12 -> 0 | I15: =I13-I9-I12 -> 0 | J15: =J13-J9-J12 -> 0
A17: Lease Liability Schedule
A18: Beginning lease liabilities | B18: INR crore | C18: ='02_Raw_Financials'!J60+'02_Raw_Financials'!J68 -> 42601.876 | D18: =C20 -> 49388.313 | E18: =D20 -> 65009.8 | F18: =E20 -> 75942.9 | G18: =F20 -> 75942.9 | H18: =G20 -> 74803.756 | I18: =H20 -> 73681.7 | J18: =I20 -> 73681.7
A19: Lease liability growth | B19: % | C19: =C20/C18-1 -> 0.15929902 | D19: =D20/D18-1 -> 0.31629926 | E19: =E20/E18-1 -> 0.16817618 | F19: 0 | G19: -0.015 | H19: -0.015 | I19: 0 | J19: 0.01
A20: Closing lease liabilities | B20: INR crore | C20: ='02_Raw_Financials'!K60+'02_Raw_Financials'!K68 -> 49388.313 | D20: ='02_Raw_Financials'!L60+'02_Raw_Financials'!L68 -> 65009.8 | E20: ='02_Raw_Financials'!M60+'02_Raw_Financials'!M68 -> 75942.9 | F20: =E20*(1+F19) -> 75942.9 | G20: =F20*(1+G19) -> 74803.756 | H20: =G20*(1+H19) -> 73681.7 | I20: =H20*(1+I19) -> 73681.7 | J20: =I20*(1+J19) -> 74418.517
A21: Current portion of total leases | B21: % | C21: =C22/C20 -> 0.23335179 | D21: =D22/D20 -> 0.15907602 | E21: =E22/E20 -> 0.15106613 | F21: 0.14 | G21: 0.13 | H21: 0.12 | I21: 0.11 | J21: 0.1
A22: Current lease liabilities | B22: INR crore | C22: ='02_Raw_Financials'!K68 -> 11524.851 | D22: ='02_Raw_Financials'!L68 -> 10341.5 | E22: ='02_Raw_Financials'!M68 -> 11472.4 | F22: =F20*F21 -> 10632.006 | G22: =G20*G21 -> 9724.4883 | H22: =H20*H21 -> 8841.804 | I22: =I20*I21 -> 8104.987 | J22: =J20*J21 -> 7441.8517
A23: Non-current lease liabilities | B23: INR crore | C23: ='02_Raw_Financials'!K60 -> 37863.462 | D23: ='02_Raw_Financials'!L60 -> 54668.3 | E23: ='02_Raw_Financials'!M60 -> 64470.5 | F23: =F20-F22 -> 65310.894 | G23: =G20-G22 -> 65079.268 | H23: =H20-H22 -> 64839.896 | I23: =I20-I22 -> 65576.713 | J23: =J20-J22 -> 66976.665
A24: Lease balance-sheet check | B24: INR crore | C24: =C20-C22-C23 -> 0 | D24: =D20-D22-D23 -> 0 | E24: =E20-E22-E23 -> 0 | F24: =F20-F22-F23 -> 0 | G24: =G20-G22-G23 -> 0 | H24: =H20-H22-H23 -> 0 | I24: =I20-I22-I23 -> 0 | J24: =J20-J22-J23 -> 0
A25: Lease liabilities / ending fleet | B25: INR crore / aircraft | C25: =C20/C13 -> 134.57306 | D25: =D20/D13 -> 149.79217 | E25: =E20/E13 -> 172.20612 | F25: =F20/F13 -> 160.55581 | G25: =G20/G13 -> 146.387 | H25: =H20/H13 -> 133.72359 | I25: =I20/I13 -> 125.09627 | J25: =J20/J13 -> 119.26044
A26: Lease liabilities / ROU assets | B26: x | C26: =C20/C32 -> 1.4440053 | D26: =D20/D32 -> 1.3247327 | E26: =E20/E32 -> 1.4589253 | F26: =F20/F32 -> 1.430319 | G26: =G20/G32 -> 1.394915 | H26: =H20/H32 -> 1.3603874 | I26: =I20/I32 -> 1.3337132 | J26: =J20/J32 -> 1.3206376
A27: Lease liabilities / EBITDAR | B27: x | C27: =C20/'06_Operating_Model'!C73 -> 2.6168583 | D27: =D20/'06_Operating_Model'!D73 -> 2.7970708 | E27: =E20/'06_Operating_Model'!E73 -> 4.8943003 | F27: =F20/'06_Operating_Model'!F73 -> 4.2958394 | G27: =G20/'06_Operating_Model'!G73 -> 3.4940509 | H27: =H20/'06_Operating_Model'!H73 -> 2.9972368 | I27: =I20/'06_Operating_Model'!I73 -> 2.6834067 | J27: =J20/'06_Operating_Model'!J73 -> 2.4916203
A29: ROU and Owned-Asset Schedule
A30: Beginning ROU assets | B30: INR crore | C30: ='02_Raw_Financials'!J34 -> 26536.495 | D30: =C32 -> 34202.308 | E30: =D32 -> 49073.9 | F30: =E32 -> 52054 | G30: =F32 -> 53095.08 | H30: =G32 -> 53626.031 | I30: =H32 -> 54162.291 | J30: =I32 -> 55245.537
A31: ROU asset growth | B31: % | C31: =C32/C30-1 -> 0.28887813 | D31: =D32/D30-1 -> 0.43481253 | E31: =E32/E30-1 -> 0.060726781 | F31: 0.02 | G31: 0.01 | H31: 0.01 | I31: 0.02 | J31: 0.02
A32: Closing ROU assets | B32: INR crore | C32: ='02_Raw_Financials'!K34 -> 34202.308 | D32: ='02_Raw_Financials'!L34 -> 49073.9 | E32: ='02_Raw_Financials'!M34 -> 52054 | F32: =E32*(1+F31) -> 53095.08 | G32: =F32*(1+G31) -> 53626.031 | H32: =G32*(1+H31) -> 54162.291 | I32: =H32*(1+I31) -> 55245.537 | J32: =I32*(1+J31) -> 56350.448
A33: Property, plant and equipment | B33: INR crore | C33: ='02_Raw_Financials'!K33 -> 1902.912 | D33: ='02_Raw_Financials'!L33 -> 2677.9 | E33: ='02_Raw_Financials'!M33 -> 11087.1 | F33: =E33*(1+F34) -> 13082.778 | G33: =F33*(1+G34) -> 15045.195 | H33: =G33*(1+H34) -> 16850.618 | I33: =H33*(1+I34) -> 18535.68 | J33: =I33*(1+J34) -> 20018.534
A34: PPE growth | B34: % | C34: =C33/'02_Raw_Financials'!J33-1 -> 0.71253158 | D34: =D33/C33-1 -> 0.40726424 | E34: =E33/D33-1 -> 3.1402218 | F34: 0.18 | G34: 0.15 | H34: 0.12 | I34: 0.1 | J34: 0.08
A35: Total aviation fixed assets | B35: INR crore | C35: =SUM(C32:C33) -> 36105.22 | D35: =SUM(D32:D33) -> 51751.8 | E35: =SUM(E32:E33) -> 63141.1 | F35: =SUM(F32:F33) -> 66177.858 | G35: =SUM(G32:G33) -> 68671.226 | H35: =SUM(H32:H33) -> 71012.909 | I35: =SUM(I32:I33) -> 73781.217 | J35: =SUM(J32:J33) -> 76368.982
A36: Depreciation and amortisation | B36: INR crore | C36: ='06_Operating_Model'!C67 -> 6425.729 | D36: ='06_Operating_Model'!D67 -> 8680.2 | E36: ='06_Operating_Model'!E67 -> 10808.2 | F36: ='06_Operating_Model'!F67 -> 11515.736 | G36: ='06_Operating_Model'!G67 -> 12961.16 | H36: ='06_Operating_Model'!H67 -> 14624.349 | I36: ='06_Operating_Model'!I67 -> 16292.051 | J36: ='06_Operating_Model'!J67 -> 17990.806
A37: D&A / closing fixed assets | B37: % | C37: =C36/C35 -> 0.1779723 | D37: =D36/D35 -> 0.1677275 | E37: =E36/E35 -> 0.17117535 | F37: =F36/F35 -> 0.17401191 | G37: =G36/G35 -> 0.18874222 | H37: =H36/H35 -> 0.2059393 | I37: =I36/I35 -> 0.22081571 | J37: =J36/J35 -> 0.2355774
A38: ROU growth less fleet growth | B38: % | C38: =C31-C14 -> 0.081641286 | D38: =D31-D14 -> 0.25225122 | E38: =E31-E14 -> 0.044597749 | F38: =F31-F14 -> -0.052562358 | G38: =G31-G14 -> -0.070338266 | H38: =H31-H14 -> -0.068277886 | I38: =I31-I14 -> -0.048965517 | J38: =J31-J14 -> -0.03942275
A40: Reported owned aircraft | B40: aircraft | E40: 36
A41: Net owned aircraft additions | B41: aircraft | F41: 10 | G41: 10 | H41: 12 | I41: 12 | J41: 12
A42: Ending owned aircraft | B42: aircraft | E42: =E40 -> 36 | F42: =E42+F41 -> 46 | G42: =F42+G41 -> 56 | H42: =G42+H41 -> 68 | I42: =H42+I41 -> 80 | J42: =I42+J41 -> 92
A43: Owned aircraft share | B43: % | E43: =E42/E13 -> 0.081632653 | F43: =F42/F13 -> 0.097251586 | G43: =G42/G13 -> 0.10958904 | H43: =H42/H13 -> 0.12341198 | I43: =I42/I13 -> 0.13582343 | J43: =J42/J13 -> 0.1474359
A44: Finance-lease aircraft | B44: aircraft | E44: 53
A45: Owned + finance-lease aircraft | B45: aircraft | E45: =E40+E44 -> 89
A46: Controlled ownership share | B46: % | E46: =E45/E13 -> 0.20181406
A47: Aircraft and engine rentals | B47: INR crore | C47: ='06_Operating_Model'!C72 -> 1075.195 | D47: ='06_Operating_Model'!D72 -> 3010.3 | E47: ='06_Operating_Model'!E72 -> 2084.7 | F47: ='06_Operating_Model'!F72 -> 2068.7372 | G47: ='06_Operating_Model'!G72 -> 2147.5529 | H47: ='06_Operating_Model'!H72 -> 2234.9249 | I47: ='06_Operating_Model'!I72 -> 2307.6073 | J47: ='06_Operating_Model'!J72 -> 2361.7639
A48: Aircraft rentals / ASK | B48: INR / ASK | C48: ='06_Operating_Model'!C70 -> 0.077185571 | D48: ='06_Operating_Model'!D70 -> 0.19113016 | E48: ='06_Operating_Model'!E70 -> 0.12092227 | F48: ='06_Operating_Model'!F70 -> 0.11487616 | G48: ='06_Operating_Model'!G70 -> 0.10913235 | H48: ='06_Operating_Model'!H70 -> 0.10367573 | I48: ='06_Operating_Model'!I70 -> 0.098491948 | J48: ='06_Operating_Model'!J70 -> 0.09356735
A50: Model Treatment and Sources
A51: Lease liability definition | B51: Management / accounting | C51: Audited consolidated lease liabilities used; management's ~INR 53,500 crore lease metric is narrower.
A52: Forecast lease balances | B52: Analyst assumption | C52: Analyst assumption: lease balances stay broadly stable as ownership rises and damp leases are returned.
A53: Owned aircraft additions | B53: Analyst assumption | C53: Analyst assumption: annual owned additions; management gave direction, not yearly acquisition guidance.
A54: Source | B54: Documents | C54: FY2026 Audited Consolidated Results; Q4 FY2026 Earnings Call Transcript.
A62: Working Capital and Finance Schedule
A63: Revenue | B63: INR crore | C63: ='07_Income_Statement'!C11 -> 68904.342 | D63: ='07_Income_Statement'!D11 -> 80802.9 | E63: ='07_Income_Statement'!E11 -> 84961.9 | F63: ='07_Income_Statement'!F11 -> 95930.314 | G63: ='07_Income_Statement'!G11 -> 109058.14 | H63: ='07_Income_Statement'!H11 -> 123688.15 | I63: ='07_Income_Statement'!I11 -> 138587.84 | J63: ='07_Income_Statement'!J11 -> 153031.25
A64: Net operating working capital | B64: INR crore | C64: =SUM('02_Raw_Financials'!K45,'02_Raw_Financials'!K47,'02_Raw_Financials'!K51,'02_Raw_Financials'!K52)-SUM('02_Raw_Financials'!K69:'02_Raw_Financials'!K72,'02_Raw_Financials'!K74:'02_Raw_Financials'!K75) -> -13817.297 | D64: =SUM('02_Raw_Financials'!L45,'02_Raw_Financials'!L47,'02_Raw_Financials'!L51,'02_Raw_Financials'!L52)-SUM('02_Raw_Financials'!L69:'02_Raw_Financials'!L72,'02_Raw_Financials'!L74:'02_Raw_Financials'!L75) -> -15107.8 | E64: =SUM('02_Raw_Financials'!M45,'02_Raw_Financials'!M47,'02_Raw_Financials'!M51,'02_Raw_Financials'!M52)-SUM('02_Raw_Financials'!M69:'02_Raw_Financials'!M72,'02_Raw_Financials'!M74:'02_Raw_Financials'!M75) -> -16801.9 | F64: =F63*F65 -> -18706.411 | G64: =G63*G65 -> -21048.221 | H64: =H63*H65 -> -23624.436 | I64: =I63*I65 -> -26331.689 | J64: =J63*J65 -> -29075.937
A65: Net operating working capital / revenue | B65: % | C65: =C64/C63 -> -0.20052868 | D65: =D64/D63 -> -0.18697101 | E65: =E64/E63 -> -0.19775805 | F65: -0.195 | G65: -0.193 | H65: -0.191 | I65: -0.19 | J65: -0.19
A66: Change in net operating working capital | B66: INR crore | C66: =C64-(SUM('02_Raw_Financials'!J45,'02_Raw_Financials'!J47,'02_Raw_Financials'!J51,'02_Raw_Financials'!J52)-SUM('02_Raw_Financials'!J69:'02_Raw_Financials'!J72,'02_Raw_Financials'!J74:'02_Raw_Financials'!J75)) -> -5349.831 | D66: =D64-C64 -> -1290.503 | E66: =E64-D64 -> -1694.1 | F66: =F64-E64 -> -1904.5113 | G66: =G64-F64 -> -2341.8097 | H66: =H64-G64 -> -2576.2148 | I66: =I64-H64 -> -2707.2531 | J66: =J64-I64 -> -2744.248
A67: Cash capital expenditure | B67: INR crore | C67: =-'02_Raw_Financials'!K92 -> 1102.645 | D67: =-'02_Raw_Financials'!L92 -> 1604.8 | E67: =-'02_Raw_Financials'!M92 -> 2271.8 | F67: =F63*F68 -> 3357.561 | G67: =G63*G68 -> 4362.3256 | H67: =H63*H68 -> 4947.5258 | I67: =I63*I68 -> 4850.5743 | J67: =J63*J68 -> 5356.0936
A68: Cash capital expenditure / revenue | B68: % | C68: =C67/C63 -> 0.016002547 | D68: =D67/D63 -> 0.019860673 | E68: =E67/E63 -> 0.026739044 | F68: 0.035 | G68: 0.04 | H68: 0.04 | I68: 0.035 | J68: 0.035
A70: Finance Cost Schedule
A71: Gross borrowings | B71: INR crore | C71: =SUM('02_Raw_Financials'!K59,'02_Raw_Financials'!K67) -> 1891.707 | D71: =SUM('02_Raw_Financials'!L59,'02_Raw_Financials'!L67) -> 1800 | E71: =SUM('02_Raw_Financials'!M59,'02_Raw_Financials'!M67) -> 1806.3 | F71: =E71*(1+F72) -> 1806.3 | G71: =F71*(1+G72) -> 1806.3 | H71: =G71*(1+H72) -> 1806.3 | I71: =H71*(1+I72) -> 1806.3 | J71: =I71*(1+J72) -> 1806.3
A72: Borrowing growth | B72: % | C72: =IFERROR(C71/SUM('02_Raw_Financials'!J59,'02_Raw_Financials'!J67)-1,0) -> -0.1601137 | D72: =IFERROR(D71/C71-1,0) -> -0.048478438 | E72: =IFERROR(E71/D71-1,0) -> 0.0035 | F72: 0 | G72: 0 | H72: 0 | I72: 0 | J72: 0
A73: Lease liabilities | B73: INR crore | C73: =C20 -> 49388.313 | D73: =D20 -> 65009.8 | E73: =E20 -> 75942.9 | F73: =F20 -> 75942.9 | G73: =G20 -> 74803.756 | H73: =H20 -> 73681.7 | I73: =I20 -> 73681.7 | J73: =J20 -> 74418.517
A74: Lease-adjusted gross debt | B74: INR crore | C74: =SUM(C71,C73) -> 51280.02 | D74: =SUM(D71,D73) -> 66809.8 | E74: =SUM(E71,E73) -> 77749.2 | F74: =SUM(F71,F73) -> 77749.2 | G74: =SUM(G71,G73) -> 76610.056 | H74: =SUM(H71,H73) -> 75488 | I74: =SUM(I71,I73) -> 75488 | J74: =SUM(J71,J73) -> 76224.817
A75: Average lease-adjusted gross debt | B75: INR crore | C75: =AVERAGE(SUM('02_Raw_Financials'!J59,'02_Raw_Financials'!J60,'02_Raw_Financials'!J67,'02_Raw_Financials'!J68),C74) -> 48067.117 | D75: =AVERAGE(C74,D74) -> 59044.91 | E75: =AVERAGE(D74,E74) -> 72279.5 | F75: =AVERAGE(E74,F74) -> 77749.2 | G75: =AVERAGE(F74,G74) -> 77179.628 | H75: =AVERAGE(G74,H74) -> 76049.028 | I75: =AVERAGE(H74,I74) -> 75488 | J75: =AVERAGE(I74,J74) -> 75856.409
A76: Finance-cost rate on average debt | B76: % | C76: ='07_Income_Statement'!C32/C75 -> 0.086740256 | D76: ='07_Income_Statement'!D32/D75 -> 0.086036205 | E76: ='07_Income_Statement'!E32/E75 -> 0.081500287 | F76: 0.08 | G76: 0.078 | H76: 0.076 | I76: 0.075 | J76: 0.075
A77: Finance costs | B77: INR crore | C77: ='07_Income_Statement'!C32 -> 4169.354 | D77: ='07_Income_Statement'!D32 -> 5080 | E77: ='07_Income_Statement'!E32 -> 5890.8 | F77: =F75*F76 -> 6219.936 | G77: =G75*G76 -> 6020.011 | H77: =H75*H76 -> 5779.7262 | I77: =I75*I76 -> 5661.6 | J77: =J75*J76 -> 5689.2306
A80: Valuation Date Liquidity Bridge
A81: Cash and cash equivalents | B81: INR crore | C81: ='02_Raw_Financials'!K48 -> 695.277 | D81: ='02_Raw_Financials'!L48 -> 1073.1 | E81: ='02_Raw_Financials'!M48 -> 1323.9
A82: Current investments | B82: INR crore | C82: ='02_Raw_Financials'!K46 -> 15571.123 | D82: ='02_Raw_Financials'!L46 -> 24774.8 | E82: ='02_Raw_Financials'!M46 -> 25743.8
A83: Other bank balances | B83: INR crore | C83: ='02_Raw_Financials'!K49 -> 16025.33 | D83: ='02_Raw_Financials'!L49 -> 17889.8 | E83: ='02_Raw_Financials'!M49 -> 22675.4
A84: Total liquidity | B84: INR crore | C84: =SUM(C81:C83) -> 32291.73 | D84: =SUM(D81:D83) -> 43737.7 | E84: =SUM(E81:E83) -> 49743.1
A85: Management-reported free cash | B85: INR crore | E85: 36216.3
A86: Lease-adjusted net debt for valuation | B86: INR crore | E86: =E74-E85 -> 41532.9
A87: Equity bridge treatment | C87: Lease liabilities are treated as debt; only management-reported free cash is deducted. Restricted cash is excluded.
A88: Source | C88: IndiGo FY2026 results press release

Sheet 09_Cash_Flow
A1: Unlevered Free Cash Flow
A2: InterGlobe Aviation Limited | INR crore | FY2024A-FY2031E
A3: Cash flow before financing; lease liabilities are treated as debt in the equity bridge.
A5: Metric | B5: Unit | C5: FY2024A | D5: FY2025A | E5: FY2026A | F5: FY2027E | G5: FY2028E | H5: FY2029E | I5: FY2030E | J5: FY2031E
A6: Period | C6: Actual | D6: Actual | E6: Actual | F6: Forecast | G6: Forecast | H6: Forecast | I6: Forecast | J6: Forecast
A8: Unlevered Free Cash Flow
A9: Operating EBIT excluding other income | B9: INR crore | C9: ='07_Income_Statement'!C24-'07_Income_Statement'!C13 -> 9045.387 | D9: ='07_Income_Statement'!D24-'07_Income_Statement'!D13 -> 8256.3 | E9: ='07_Income_Statement'!E24-'07_Income_Statement'!E13 -> -1927.8 | F9: ='07_Income_Statement'!F24-'07_Income_Statement'!F13 -> 256.5591 | G9: ='07_Income_Statement'!G24-'07_Income_Statement'!G13 -> 2155.9694 | H9: ='07_Income_Statement'!H24-'07_Income_Statement'!H13 -> 3394.8503 | I9: ='07_Income_Statement'!I24-'07_Income_Statement'!I13 -> 4285.2104 | J9: ='07_Income_Statement'!J24-'07_Income_Statement'!J13 -> 4924.0117
A10: Normalised tax rate | B10: % | C10: ='07_Income_Statement'!F36 -> 0.252 | D10: ='07_Income_Statement'!F36 -> 0.252 | E10: ='07_Income_Statement'!F36 -> 0.252 | F10: ='07_Income_Statement'!F36 -> 0.252 | G10: ='07_Income_Statement'!F36 -> 0.252 | H10: ='07_Income_Statement'!F36 -> 0.252 | I10: ='07_Income_Statement'!F36 -> 0.252 | J10: ='07_Income_Statement'!F36 -> 0.252
A11: Tax on EBIT | B11: INR crore | C11: =MAX(C9,0)*C10 -> 2279.4375 | D11: =MAX(D9,0)*D10 -> 2080.5876 | E11: =MAX(E9,0)*E10 -> 0 | F11: =MAX(F9,0)*F10 -> 64.652892 | G11: =MAX(G9,0)*G10 -> 543.3043 | H11: =MAX(H9,0)*H10 -> 855.50227 | I11: =MAX(I9,0)*I10 -> 1079.873 | J11: =MAX(J9,0)*J10 -> 1240.851
A12: NOPAT | B12: INR crore | C12: =C9-C11 -> 6765.9495 | D12: =D9-D11 -> 6175.7124 | E12: =E9-E11 -> -1927.8 | F12: =F9-F11 -> 191.9062 | G12: =G9-G11 -> 1612.6651 | H12: =H9-H11 -> 2539.348 | I12: =I9-I11 -> 3205.3374 | J12: =J9-J11 -> 3683.1608
A13: Depreciation and amortisation | B13: INR crore | C13: ='07_Income_Statement'!C20 -> 6425.729 | D13: ='07_Income_Statement'!D20 -> 8680.2 | E13: ='07_Income_Statement'!E20 -> 10808.2 | F13: ='07_Income_Statement'!F20 -> 11515.736 | G13: ='07_Income_Statement'!G20 -> 12961.16 | H13: ='07_Income_Statement'!H20 -> 14624.349 | I13: ='07_Income_Statement'!I20 -> 16292.051 | J13: ='07_Income_Statement'!J20 -> 17990.806
A14: Asset reinvestment | B14: INR crore | C14: ='08_Balance_Sheet'!C67 -> 1102.645 | D14: ='08_Balance_Sheet'!D67 -> 1604.8 | E14: ='08_Balance_Sheet'!E67 -> 2271.8 | F14: =F13+'08_Balance_Sheet'!F35-'08_Balance_Sheet'!E35 -> 14552.494 | G14: =G13+'08_Balance_Sheet'!G35-'08_Balance_Sheet'!F35 -> 15454.527 | H14: =H13+'08_Balance_Sheet'!H35-'08_Balance_Sheet'!G35 -> 16966.033 | I14: =I13+'08_Balance_Sheet'!I35-'08_Balance_Sheet'!H35 -> 19060.359 | J14: =J13+'08_Balance_Sheet'!J35-'08_Balance_Sheet'!I35 -> 20578.571
A15: Change in net operating working capital | B15: INR crore | C15: ='08_Balance_Sheet'!C66 -> -5349.831 | D15: ='08_Balance_Sheet'!D66 -> -1290.503 | E15: ='08_Balance_Sheet'!E66 -> -1694.1 | F15: ='08_Balance_Sheet'!F66 -> -1904.5113 | G15: ='08_Balance_Sheet'!G66 -> -2341.8097 | H15: ='08_Balance_Sheet'!H66 -> -2576.2148 | I15: ='08_Balance_Sheet'!I66 -> -2707.2531 | J15: ='08_Balance_Sheet'!J66 -> -2744.248
A16: Unlevered free cash flow | B16: INR crore | C16: =C12+C13-C14-C15 -> 17438.864 | D16: =D12+D13-D14-D15 -> 14541.615 | E16: =E12+E13-E14-E15 -> 8302.7 | F16: =F12+F13-F14-F15 -> -940.34048 | G16: =G12+G13-G14-G15 -> 1461.1074 | H16: =H12+H13-H14-H15 -> 2773.8791 | I16: =I12+I13-I14-I15 -> 3144.2829 | J16: =J12+J13-J14-J15 -> 3839.6436
A17: Unlevered free cash flow margin | B17: % | C17: =C16/'07_Income_Statement'!C11 -> 0.25308803 | D17: =D16/'07_Income_Statement'!D11 -> 0.17996403 | E17: =E16/'07_Income_Statement'!E11 -> 0.097722626 | F17: =F16/'07_Income_Statement'!F11 -> -0.0098023287 | G17: =G16/'07_Income_Statement'!G11 -> 0.013397509 | H17: =H16/'07_Income_Statement'!H11 -> 0.022426394 | I17: =I16/'07_Income_Statement'!I11 -> 0.022688015 | J17: =J16/'07_Income_Statement'!J11 -> 0.025090586
A18: Forecast reinvestment | C18: D&A plus change in net PPE and ROU assets; assumes no disposals, impairments or FX revaluations.
A19: Historical reinvestment | C19: Historical columns show cash capex only; they exclude non-cash lease additions and are not comparable with forecast UFCF.
A20: Other income treatment | C20: All other income excluded for valuation; operating compensation is not separately forecast.

Sheet 10_Scenarios
A1: Operating Scenarios
A2: InterGlobe Aviation Limited | FY2027 driver cases
A3: Base case links to the operating model; bear and bull cases flex operating drivers without changing WACC or terminal growth.
A5: Assumption | B5: Bear | C5: Base | D5: Bull
A7: FY2027 ASK growth | B7: 0.025 | C7: ='06_Operating_Model'!F19 -> 0.044571429 | D7: 0.065
A8: FY2027 passenger PRASK growth | B8: 0.04 | C8: ='06_Operating_Model'!F36 -> 0.087719588 | D8: 0.12
A9: FY2027 fuel CASK growth | B9: 0.1 | C9: ='06_Operating_Model'!F52 -> 0.05 | D9: 0
A10: FY2027 ex-fuel CASK growth (including FX) | B10: 0.09 | C10: ='06_Operating_Model'!F55 -> 0.07 | D10: 0.05
A12: FY2027 revenue | B12: =('06_Operating_Model'!$E$18*(1+B$7))*('06_Operating_Model'!$E$35*(1+B$8)+'06_Operating_Model'!$F$37)*100 -> 90531.842 | C12: =('06_Operating_Model'!$E$18*(1+C$7))*('06_Operating_Model'!$E$35*(1+C$8)+'06_Operating_Model'!$F$37)*100 -> 95930.314 | D12: =('06_Operating_Model'!$E$18*(1+D$7))*('06_Operating_Model'!$E$35*(1+D$8)+'06_Operating_Model'!$F$37)*100 -> 100337.47
A13: FY2027 operating cost | B13: =('06_Operating_Model'!$E$18*(1+B$7))*('06_Operating_Model'!$E$51*(1+B$9)+'06_Operating_Model'!$E$54*(1+B$10))*100 -> 96426.416 | C13: =('06_Operating_Model'!$E$18*(1+C$7))*('06_Operating_Model'!$E$51*(1+C$9)+'06_Operating_Model'!$E$54*(1+C$10))*100 -> 95673.755 | D13: =('06_Operating_Model'!$E$18*(1+D$7))*('06_Operating_Model'!$E$51*(1+D$9)+'06_Operating_Model'!$E$54*(1+D$10))*100 -> 94900.276
A14: Operating result before other income | B14: =B12-B13 -> -5894.5735 | C14: =C12-C13 -> 256.5591 | D14: =D12-D13 -> 5437.1963
A15: Operating margin | B15: =B14/B12 -> -0.065110499 | C15: =C14/C12 -> 0.0026744319 | D15: =D14/D12 -> 0.05418909
A17: Note | B17: FY2027 operating scenarios use analyst assumptions. Valuation sensitivity is on 11_DCF.

Sheet 11_DCF
A1: Discounted Cash Flow Valuation
A2: InterGlobe Aviation Limited | INR crore except per-share values
A3: 31-Mar-2026 valuation basis. Lease debt and estimated owned/leased asset reinvestment are included.
A5: Metric | B5: Unit | C5: FY2027E | D5: FY2028E | E5: FY2029E | F5: FY2030E | G5: FY2031E
A7: Forecast Cash Flow
A8: Unlevered free cash flow | B8: INR crore | C8: ='09_Cash_Flow'!F16 -> -940.34048 | D8: ='09_Cash_Flow'!G16 -> 1461.1074 | E8: ='09_Cash_Flow'!H16 -> 2773.8791 | F8: ='09_Cash_Flow'!I16 -> 3144.2829 | G8: ='09_Cash_Flow'!J16 -> 3839.6436
A9: Discount period | B9: years | C9: 1 | D9: 2 | E9: 3 | F9: 4 | G9: 5
A10: Discount factor | B10: x | C10: =1/(1+$B$21)^C9 -> 0.89930645 | D10: =1/(1+$B$21)^D9 -> 0.8087521 | E10: =1/(1+$B$21)^E9 -> 0.72731598 | F10: =1/(1+$B$21)^F9 -> 0.65407996 | G10: =1/(1+$B$21)^G9 -> 0.58821833
A11: Present value of cash flow | B11: INR crore | C11: =C8*C10 -> -845.65426 | D11: =D8*D10 -> 1181.6737 | E11: =E8*E10 -> 2017.4866 | F11: =F8*F10 -> 2056.6124 | G11: =G8*G10 -> 2258.5487
A13: WACC Assumptions
A14: Risk-free rate | B14: 0.065
A15: Beta | B15: 1
A16: Equity risk premium | B16: 0.06
A17: Cost of equity | B17: =B14+B15*B16 -> 0.125
A18: Pre-tax cost of debt | B18: 0.08
A19: Tax rate | B19: ='07_Income_Statement'!F36 -> 0.252
A20: Debt weight | B20: 0.2
A21: WACC | B21: =B17*(1-B20)+B18*(1-B19)*B20 -> 0.111968
A22: Terminal growth | B22: 0.04
A24: Valuation Bridge
A25: Present value of forecast cash flow | B25: INR crore | C25: =SUM(C11:G11) -> 6668.6671
A26: Terminal-year cash flow | B26: INR crore | C26: =G8 -> 3839.6436
A27: Terminal value | B27: INR crore | C27: =C26*(1+B22)/(B21-B22) -> 55486.179
A28: Present value of terminal value | B28: INR crore | C28: =C27/(1+B21)^G9 -> 32637.987
A29: Enterprise value | B29: INR crore | C29: =C25+C28 -> 39306.655
A30: Less: lease-adjusted net debt (free cash basis) | B30: INR crore | C30: ='08_Balance_Sheet'!E86 -> 41532.9
A31: Equity value | B31: INR crore | C31: =MAX(C29-C30,0) -> 0
A32: Diluted shares | B32: crore shares | C32: ='07_Income_Statement'!E42 -> 38.681319
A33: Implied value per share | B33: INR per share | C33: =C31/C32 -> 0
A34: Terminal value / enterprise value | B34: % | C34: =C28/C29 -> 0.83034254
A35: WACC exceeds terminal growth | B35: status | C35: =IF(B21>B22,"OK","CHECK") -> OK
A36: Enterprise value less net debt | B36: INR crore | C36: =C29-C30 -> -2226.2454
A38: DCF Sensitivity: Value per Share
B39: WACC / TGR | C39: 0.03 | D39: =$B$22 -> 0.04 | E39: 0.05
B40: 0.1 | C40: {=MAX((SUMPRODUCT($C$8:$G$8,1/(1+$B40)^$C$9:$G$9)+($G$8*(1+C$39)/($B40-C$39))/(1+$B40)^$G$9-'08_Balance_Sheet'!$E$86)/'07_Income_Statement'!$E$42,0)} -> 13.342481 | D40: {=MAX((SUMPRODUCT($C$8:$G$8,1/(1+$B40)^$C$9:$G$9)+($G$8*(1+D$39)/($B40-D$39))/(1+$B40)^$G$9-'08_Balance_Sheet'!$E$86)/'07_Income_Statement'!$E$42,0)} -> 174.76704 | E40: {=MAX((SUMPRODUCT($C$8:$G$8,1/(1+$B40)^$C$9:$G$9)+($G$8*(1+E$39)/($B40-E$39))/(1+$B40)^$G$9-'08_Balance_Sheet'!$E$86)/'07_Income_Statement'!$E$42,0)} -> 400.76142
B41: =$B$21 -> 0.111968 | C41: {=MAX((SUMPRODUCT($C$8:$G$8,1/(1+$B41)^$C$9:$G$9)+($G$8*(1+C$39)/($B41-C$39))/(1+$B41)^$G$9-'08_Balance_Sheet'!$E$86)/'07_Income_Statement'!$E$42,0)} -> 0 | D41: {=MAX((SUMPRODUCT($C$8:$G$8,1/(1+$B41)^$C$9:$G$9)+($G$8*(1+D$39)/($B41-D$39))/(1+$B41)^$G$9-'08_Balance_Sheet'!$E$86)/'07_Income_Statement'!$E$42,0)} -> 0 | E41: {=MAX((SUMPRODUCT($C$8:$G$8,1/(1+$B41)^$C$9:$G$9)+($G$8*(1+E$39)/($B41-E$39))/(1+$B41)^$G$9-'08_Balance_Sheet'!$E$86)/'07_Income_Statement'!$E$42,0)} -> 88.030472
B42: 0.12 | C42: {=MAX((SUMPRODUCT($C$8:$G$8,1/(1+$B42)^$C$9:$G$9)+($G$8*(1+C$39)/($B42-C$39))/(1+$B42)^$G$9-'08_Balance_Sheet'!$E$86)/'07_Income_Statement'!$E$42,0)} -> 0 | D42: {=MAX((SUMPRODUCT($C$8:$G$8,1/(1+$B42)^$C$9:$G$9)+($G$8*(1+D$39)/($B42-D$39))/(1+$B42)^$G$9-'08_Balance_Sheet'!$E$86)/'07_Income_Statement'!$E$42,0)} -> 0 | E42: {=MAX((SUMPRODUCT($C$8:$G$8,1/(1+$B42)^$C$9:$G$9)+($G$8*(1+E$39)/($B42-E$39))/(1+$B42)^$G$9-'08_Balance_Sheet'!$E$86)/'07_Income_Statement'!$E$42,0)} -> 0
B43: 0.13 | C43: {=MAX((SUMPRODUCT($C$8:$G$8,1/(1+$B43)^$C$9:$G$9)+($G$8*(1+C$39)/($B43-C$39))/(1+$B43)^$G$9-'08_Balance_Sheet'!$E$86)/'07_Income_Statement'!$E$42,0)} -> 0 | D43: {=MAX((SUMPRODUCT($C$8:$G$8,1/(1+$B43)^$C$9:$G$9)+($G$8*(1+D$39)/($B43-D$39))/(1+$B43)^$G$9-'08_Balance_Sheet'!$E$86)/'07_Income_Statement'!$E$42,0)} -> 0 | E43: {=MAX((SUMPRODUCT($C$8:$G$8,1/(1+$B43)^$C$9:$G$9)+($G$8*(1+E$39)/($B43-E$39))/(1+$B43)^$G$9-'08_Balance_Sheet'!$E$86)/'07_Income_Statement'!$E$42,0)} -> 0

Sheet 12_Reverse_DCF
A1: Reverse DCF
A2: InterGlobe Aviation Limited | Market-implied cash-flow expectations
A3: Scales forecast and terminal UFCF uniformly; September price compared with a March valuation basis.
A5: Market-Implied Valuation
A6: Market price as of | C6: 07-Sep-2026 close
A7: Current market price | B7: INR per share | C7: 5001
A8: Diluted shares | B8: crore shares | C8: ='07_Income_Statement'!E42 -> 38.681319
A9: Market-implied equity value | B9: INR crore | C9: =C7*C8 -> 193445.27
A10: Lease-adjusted net debt / (cash) | B10: INR crore | C10: ='08_Balance_Sheet'!E86 -> 41532.9
A11: Market-implied enterprise value | B11: INR crore | C11: =C9+C10 -> 234978.17
A12: Base-case DCF enterprise value | B12: INR crore | C12: ='11_DCF'!C29 -> 39306.655
A13: Required forecast UFCF factor | B13: x | C13: =C11/C12 -> 5.9780762
A14: Implied FY2031E UFCF | B14: INR crore | C14: ='09_Cash_Flow'!J16*C13 -> 22953.682
A15: Implied FY2031E UFCF margin | B15: % | C15: =C14/'07_Income_Statement'!J11 -> 0.14999343
A16: Base-case FY2031E UFCF margin | B16: % | C16: ='09_Cash_Flow'!J17 -> 0.025090586
A17: Implied margin difference | B17: percentage points | C17: =C15-C16 -> 0.12490285
A20: Valuation Comparison
A21: Observed market price | C21: =C7 -> 5001
A22: Base-case DCF value | C22: ='11_DCF'!C33 -> 0
A23: DCF premium / (discount) | B23: % | C23: =C22/C21-1 -> -1
A25: Interpretation | C25: A factor below 1.0x indicates lower market-implied cash flow than the base case.
